{"_id":"feathers-hooks-common","_rev":"38-d1556bdcf50ad9e1b09156bef349d615","name":"feathers-hooks-common","description":"Useful hooks for use with Feathersjs services.","dist-tags":{"latest":"2.0.3"},"versions":{"0.0.1":{"name":"feathers-hooks-common","version":"0.0.1","description":"Useful hooks for use with Feathersjs services.","main":"lib/","directories":{"lib":"lib"},"scripts":{"copy":"rm -rf lib/ && cp -r src/ lib/","babel":"babel src/ --out-dir lib --presets babel-preset-es2015","babel:watch":"babel src/ --watch --out-dir lib --presets babel-preset-es2015","mocha":"mocha test/  --reporter spec --compilers js:babel-core/register","mocha:es6":"mocha test/ --reporter spec","eslint":"eslint src/. test/. --ext .js,.jsx .","build":"npm run copy && npm run babel","test":"npm run build && npm run eslint && npm run mocha","test:es6":"npm run eslint && npm run mocha:es6","cover":"node_modules/istanbul/lib/cli.js cover node_modules/mocha/bin/_mocha -- --reporter spec test/*","watch":"npm run copy && npm run babel:watch","git:push":"npm run build && git push origin && git push origin --tags","npm:patch":"npm version patch && npm publish","npm:minor":"npm version minor && npm publish","npm:major":"npm version major && npm publish","npm:updates":"npm-check-updates"},"repository":{"type":"git","url":"git+https://github.com/eddyystop/feathers-hooks-common.git"},"keywords":["feathers","feathersjs","hook","hooks"],"author":{"name":"John Szwaronek","email":"johnsz9999@gmail.com"},"license":"MIT","bugs":{"url":"https://github.com/eddyystop/feathers-hooks-common/issues"},"homepage":"https://github.com/eddyystop/feathers-hooks-common#readme","dependencies":{"debug":"^2.2.0","object.assign":"^4.1.0"},"devDependencies":{"babel-cli":"^6.6.5","babel-core":"^6.7.0","babel-eslint":"6.1.0","babel-plugin-add-module-exports":"^0.2.1","babel-preset-es2015":"^6.6.0","chai":"3.5.0","coveralls":"2.11.9","eslint":"3.0.1","eslint-config-airbnb":"9.0.1","eslint-plugin-import":"1.10.2","eslint-plugin-jsx-a11y":"1.5.5","eslint-plugin-react":"5.2.2","istanbul":"0.4.4","mocha":"2.5.3"},"engines":{"node":">=5.0.0","npm":">=3.8.0"},"gitHead":"f64302d26c41acdae5792207795dd2c25eb230e8","_id":"feathers-hooks-common@0.0.1","_shasum":"94e6e93749b4c22c116a74d2ebc5023accd255d7","_from":".","_npmVersion":"3.10.5","_nodeVersion":"6.2.2","_npmUser":{"name":"eddystop","email":"johnsz9999@gmail.com"},"dist":{"shasum":"94e6e93749b4c22c116a74d2ebc5023accd255d7","tarball":"https://registry.npmjs.org/feathers-hooks-common/-/feathers-hooks-common-0.0.1.tgz"},"maintainers":[{"name":"eddystop","email":"johnsz9999@gmail.com"}],"_npmOperationalInternal":{"host":"packages-12-west.internal.npmjs.com","tmp":"tmp/feathers-hooks-common-0.0.1.tgz_1468432458199_0.9146527559496462"}},"0.1.0":{"name":"feathers-hooks-common","version":"0.1.0","description":"Useful hooks for use with Feathersjs services.","main":"lib/","directories":{"lib":"lib"},"scripts":{"copy":"rm -rf lib/ && cp -r src/ lib/","babel":"babel src/ --out-dir lib --presets babel-preset-es2015","babel:watch":"babel src/ --watch --out-dir lib --presets babel-preset-es2015","mocha":"mocha test/  --reporter spec --compilers js:babel-core/register","mocha:es6":"mocha test/ --reporter spec","eslint":"eslint src/. test/. --ext .js,.jsx .","build":"npm run copy && npm run babel","test":"npm run build && npm run eslint && npm run mocha","test:es6":"npm run mocha:es6","cover":"node_modules/istanbul/lib/cli.js cover node_modules/mocha/bin/_mocha -- --reporter spec test/*","watch":"npm run copy && npm run babel:watch","git:push":"npm run build && git push origin && git push origin --tags","npm:patch":"npm version patch && npm publish","npm:minor":"npm version minor && npm publish","npm:major":"npm version major && npm publish","npm:updates":"npm-check-updates"},"repository":{"type":"git","url":"git+https://github.com/eddyystop/feathers-hooks-common.git"},"keywords":["feathers","feathersjs","hook","hooks"],"author":{"name":"John Szwaronek","email":"johnsz9999@gmail.com"},"license":"MIT","bugs":{"url":"https://github.com/eddyystop/feathers-hooks-common/issues"},"homepage":"https://github.com/eddyystop/feathers-hooks-common#readme","dependencies":{"debug":"^2.2.0","feathers-hooks-utils":"^0.1.1","object.assign":"^4.0.4"},"devDependencies":{"babel-cli":"^6.10.1","babel-core":"^6.10.4","babel-eslint":"6.1.0","babel-plugin-add-module-exports":"^0.2.1","babel-preset-es2015":"^6.9.0","chai":"3.5.0","coveralls":"2.11.9","eslint":"3.0.1","eslint-config-airbnb":"9.0.1","eslint-plugin-import":"1.10.2","eslint-plugin-jsx-a11y":"1.5.5","eslint-plugin-react":"5.2.2","istanbul":"0.4.4","mocha":"2.5.3"},"engines":{"node":">=5.0.0","npm":">=3.8.0"},"gitHead":"ba9732d058c4be8043f40b8cbd3c9decde3b0c94","_id":"feathers-hooks-common@0.1.0","_shasum":"1b5ad8deeefdb486c9eeedf1243abe229cf7301a","_from":".","_npmVersion":"3.10.5","_nodeVersion":"6.2.2","_npmUser":{"name":"eddystop","email":"johnsz9999@gmail.com"},"dist":{"shasum":"1b5ad8deeefdb486c9eeedf1243abe229cf7301a","tarball":"https://registry.npmjs.org/feathers-hooks-common/-/feathers-hooks-common-0.1.0.tgz"},"maintainers":[{"name":"eddystop","email":"johnsz9999@gmail.com"}],"_npmOperationalInternal":{"host":"packages-16-east.internal.npmjs.com","tmp":"tmp/feathers-hooks-common-0.1.0.tgz_1468520716533_0.6581185823306441"}},"0.1.1":{"name":"feathers-hooks-common","version":"0.1.1","description":"Useful hooks for use with Feathersjs services.","main":"lib/","directories":{"lib":"lib"},"scripts":{"copy":"rm -rf lib/ && cp -r src/ lib/","babel":"babel src/ --out-dir lib --presets babel-preset-es2015","babel:watch":"babel src/ --watch --out-dir lib --presets babel-preset-es2015","mocha":"mocha test/  --reporter spec --compilers js:babel-core/register","mocha:es6":"mocha test/ --reporter spec","eslint":"eslint src/. test/. --ext .js,.jsx .","build":"npm run copy && npm run babel","test":"npm run build && npm run eslint && npm run mocha","test:es6":"npm run mocha:es6","cover":"node_modules/istanbul/lib/cli.js cover node_modules/mocha/bin/_mocha -- --reporter spec test/*","watch":"npm run copy && npm run babel:watch","git:push":"npm run build && git push origin && git push origin --tags","npm:patch":"npm version patch && npm publish","npm:minor":"npm version minor && npm publish","npm:major":"npm version major && npm publish","npm:updates":"npm-check-updates"},"repository":{"type":"git","url":"git+https://github.com/eddyystop/feathers-hooks-common.git"},"keywords":["feathers","feathersjs","hook","hooks"],"author":{"name":"John Szwaronek","email":"johnsz9999@gmail.com"},"license":"MIT","bugs":{"url":"https://github.com/eddyystop/feathers-hooks-common/issues"},"homepage":"https://github.com/eddyystop/feathers-hooks-common#readme","dependencies":{"debug":"^2.2.0","feathers-hooks-utils":"^0.1.1","object.assign":"^4.0.4"},"devDependencies":{"babel-cli":"^6.10.1","babel-core":"^6.10.4","babel-eslint":"6.1.0","babel-plugin-add-module-exports":"^0.2.1","babel-preset-es2015":"^6.9.0","chai":"3.5.0","coveralls":"2.11.9","eslint":"3.0.1","eslint-config-airbnb":"9.0.1","eslint-plugin-import":"1.10.2","eslint-plugin-jsx-a11y":"1.5.5","eslint-plugin-react":"5.2.2","istanbul":"0.4.4","mocha":"2.5.3"},"engines":{"node":">=5.0.0","npm":">=3.8.0"},"gitHead":"04b6a5427c466ee022fb604977766e95ba76b954","_id":"feathers-hooks-common@0.1.1","_shasum":"5b02ff3eb4904276128de21ad8baa7d317fc402c","_from":".","_npmVersion":"3.10.5","_nodeVersion":"6.2.2","_npmUser":{"name":"eddystop","email":"johnsz9999@gmail.com"},"dist":{"shasum":"5b02ff3eb4904276128de21ad8baa7d317fc402c","tarball":"https://registry.npmjs.org/feathers-hooks-common/-/feathers-hooks-common-0.1.1.tgz"},"maintainers":[{"name":"eddystop","email":"johnsz9999@gmail.com"}],"_npmOperationalInternal":{"host":"packages-16-east.internal.npmjs.com","tmp":"tmp/feathers-hooks-common-0.1.1.tgz_1468546219380_0.32876526145264506"}},"0.1.2":{"name":"feathers-hooks-common","version":"0.1.2","description":"Useful hooks for use with Feathersjs services.","main":"lib/","directories":{"lib":"lib"},"scripts":{"copy":"rm -rf lib/ && cp -r src/ lib/","babel":"babel src/ --out-dir lib --presets babel-preset-es2015","babel:watch":"babel src/ --watch --out-dir lib --presets babel-preset-es2015","mocha":"mocha test/  --reporter spec --compilers js:babel-core/register","mocha:es6":"mocha test/ --reporter spec","eslint":"eslint src/. test/. --ext .js,.jsx .","build":"npm run copy && npm run babel","test":"npm run build && npm run eslint && npm run mocha","test:es6":"npm run mocha:es6","cover":"node_modules/istanbul/lib/cli.js cover node_modules/mocha/bin/_mocha -- --reporter spec test/*","watch":"npm run copy && npm run babel:watch","git:push":"npm run build && git push origin && git push origin --tags","npm:patch":"npm version patch && npm publish","npm:minor":"npm version minor && npm publish","npm:major":"npm version major && npm publish","npm:updates":"npm-check-updates"},"repository":{"type":"git","url":"git+https://github.com/eddyystop/feathers-hooks-common.git"},"keywords":["feathers","feathersjs","hook","hooks"],"author":{"name":"John Szwaronek","email":"johnsz9999@gmail.com"},"license":"MIT","bugs":{"url":"https://github.com/eddyystop/feathers-hooks-common/issues"},"homepage":"https://github.com/eddyystop/feathers-hooks-common#readme","dependencies":{"debug":"^2.2.0","feathers-hooks-utils":"^0.1.1","object.assign":"^4.0.4"},"devDependencies":{"babel-cli":"^6.10.1","babel-core":"^6.10.4","babel-eslint":"6.1.0","babel-plugin-add-module-exports":"^0.2.1","babel-preset-es2015":"^6.9.0","chai":"3.5.0","coveralls":"2.11.9","eslint":"3.0.1","eslint-config-airbnb":"9.0.1","eslint-plugin-import":"1.10.2","eslint-plugin-jsx-a11y":"1.5.5","eslint-plugin-react":"5.2.2","istanbul":"0.4.4","mocha":"2.5.3"},"engines":{"node":">=5.0.0","npm":">=3.8.0"},"gitHead":"197b6cfb6601b827e321da2e4e9f31da7a1c5800","_id":"feathers-hooks-common@0.1.2","_shasum":"1ac634f02557a85ba549af24bb0b69227c8e9e90","_from":".","_npmVersion":"3.10.5","_nodeVersion":"6.2.2","_npmUser":{"name":"eddystop","email":"johnsz9999@gmail.com"},"dist":{"shasum":"1ac634f02557a85ba549af24bb0b69227c8e9e90","tarball":"https://registry.npmjs.org/feathers-hooks-common/-/feathers-hooks-common-0.1.2.tgz"},"maintainers":[{"name":"eddystop","email":"johnsz9999@gmail.com"}],"_npmOperationalInternal":{"host":"packages-12-west.internal.npmjs.com","tmp":"tmp/feathers-hooks-common-0.1.2.tgz_1468546342844_0.5372557651717216"}},"0.1.3":{"name":"feathers-hooks-common","version":"0.1.3","description":"Useful hooks for use with Feathersjs services.","main":"lib/","directories":{"lib":"lib"},"scripts":{"copy":"rm -rf lib/ && cp -r src/ lib/","babel":"babel src/ --out-dir lib --presets babel-preset-es2015","babel:watch":"babel src/ --watch --out-dir lib --presets babel-preset-es2015","mocha":"mocha test/  --reporter spec --compilers js:babel-core/register","mocha:es6":"mocha test/ --reporter spec","eslint":"eslint src/. test/. --ext .js,.jsx .","build":"npm run copy && npm run babel","test":"npm run build && npm run eslint && npm run mocha","test:es6":"npm run mocha:es6","cover":"node_modules/istanbul/lib/cli.js cover node_modules/mocha/bin/_mocha -- --reporter spec test/*","watch":"npm run copy && npm run babel:watch","git:push":"npm run build && git push origin && git push origin --tags","npm:patch":"npm version patch && npm publish","npm:minor":"npm version minor && npm publish","npm:major":"npm version major && npm publish","npm:updates":"npm-check-updates"},"repository":{"type":"git","url":"git+https://github.com/eddyystop/feathers-hooks-common.git"},"keywords":["feathers","feathersjs","hook","hooks"],"author":{"name":"John Szwaronek","email":"johnsz9999@gmail.com"},"license":"MIT","bugs":{"url":"https://github.com/eddyystop/feathers-hooks-common/issues"},"homepage":"https://github.com/eddyystop/feathers-hooks-common#readme","dependencies":{"debug":"^2.2.0","feathers-hooks-utils":"^0.1.1","object.assign":"^4.0.4"},"devDependencies":{"babel-cli":"^6.10.1","babel-core":"^6.10.4","babel-eslint":"6.1.0","babel-plugin-add-module-exports":"^0.2.1","babel-preset-es2015":"^6.9.0","chai":"3.5.0","coveralls":"2.11.9","eslint":"3.0.1","eslint-config-airbnb":"9.0.1","eslint-plugin-import":"1.10.2","eslint-plugin-jsx-a11y":"1.5.5","eslint-plugin-react":"5.2.2","istanbul":"0.4.4","mocha":"2.5.3"},"engines":{"node":">=5.0.0","npm":">=3.8.0"},"gitHead":"b074513d792971a78387a4acb61b810753ea3270","_id":"feathers-hooks-common@0.1.3","_shasum":"d26457ca25ff8d51a0f27a7e871286d0550cd9ee","_from":".","_npmVersion":"3.10.5","_nodeVersion":"6.2.2","_npmUser":{"name":"eddystop","email":"johnsz9999@gmail.com"},"dist":{"shasum":"d26457ca25ff8d51a0f27a7e871286d0550cd9ee","tarball":"https://registry.npmjs.org/feathers-hooks-common/-/feathers-hooks-common-0.1.3.tgz"},"maintainers":[{"name":"eddystop","email":"johnsz9999@gmail.com"}],"_npmOperationalInternal":{"host":"packages-16-east.internal.npmjs.com","tmp":"tmp/feathers-hooks-common-0.1.3.tgz_1468585849563_0.6894283429719508"}},"0.2.0":{"name":"feathers-hooks-common","version":"0.2.0","description":"Useful hooks for use with Feathersjs services.","main":"lib/","directories":{"lib":"lib"},"scripts":{"copy":"rm -rf lib/ && cp -r src/ lib/","babel":"babel src/ --out-dir lib --presets babel-preset-es2015","babel:watch":"babel src/ --watch --out-dir lib --presets babel-preset-es2015","mocha":"mocha test/  --reporter spec --compilers js:babel-core/register","mocha:es6":"mocha test/ --reporter spec","eslint":"eslint src/. test/. --ext .js,.jsx .","build":"npm run copy && npm run babel","test":"npm run build && npm run eslint && npm run mocha","test:es6":"npm run mocha:es6","cover":"node_modules/istanbul/lib/cli.js cover node_modules/mocha/bin/_mocha -- --reporter spec test/*","watch":"npm run copy && npm run babel:watch","git:push":"npm run build && git push origin && git push origin --tags","npm:patch":"npm version patch && npm publish","npm:minor":"npm version minor && npm publish","npm:major":"npm version major && npm publish","npm:updates":"npm-check-updates"},"repository":{"type":"git","url":"git+https://github.com/eddyystop/feathers-hooks-common.git"},"keywords":["feathers","feathersjs","hook","hooks"],"author":{"name":"John Szwaronek","email":"johnsz9999@gmail.com"},"license":"MIT","bugs":{"url":"https://github.com/eddyystop/feathers-hooks-common/issues"},"homepage":"https://github.com/eddyystop/feathers-hooks-common#readme","dependencies":{"debug":"^2.2.0","feathers-hooks-utils":"^0.1.1","object.assign":"^4.0.4"},"devDependencies":{"babel-cli":"^6.10.1","babel-core":"^6.10.4","babel-eslint":"6.1.0","babel-plugin-add-module-exports":"^0.2.1","babel-preset-es2015":"^6.9.0","chai":"3.5.0","coveralls":"2.11.9","eslint":"3.0.1","eslint-config-airbnb":"9.0.1","eslint-plugin-import":"1.10.2","eslint-plugin-jsx-a11y":"1.5.5","eslint-plugin-react":"5.2.2","istanbul":"0.4.4","mocha":"2.5.3"},"engines":{"node":">=5.0.0","npm":">=3.8.0"},"gitHead":"d496c07c9ef9fb7484a2acff546f0059d83718dc","_id":"feathers-hooks-common@0.2.0","_shasum":"d497b69c24ee36b42969ceeae2e90748a312c53b","_from":".","_npmVersion":"3.10.5","_nodeVersion":"6.2.2","_npmUser":{"name":"eddystop","email":"johnsz9999@gmail.com"},"dist":{"shasum":"d497b69c24ee36b42969ceeae2e90748a312c53b","tarball":"https://registry.npmjs.org/feathers-hooks-common/-/feathers-hooks-common-0.2.0.tgz"},"maintainers":[{"name":"eddystop","email":"johnsz9999@gmail.com"}],"_npmOperationalInternal":{"host":"packages-16-east.internal.npmjs.com","tmp":"tmp/feathers-hooks-common-0.2.0.tgz_1468586809571_0.1095718047581613"}},"1.0.0":{"name":"feathers-hooks-common","version":"1.0.0","description":"Useful hooks for use with Feathersjs services.","main":"lib/","directories":{"lib":"lib"},"scripts":{"copy":"rm -rf lib/ && cp -r src/ lib/","babel":"babel src/ --out-dir lib --presets babel-preset-es2015","babel:watch":"babel src/ --watch --out-dir lib --presets babel-preset-es2015","mocha":"mocha test/  --reporter spec --compilers js:babel-core/register","mocha:es6":"mocha test/ --reporter spec","eslint":"eslint src/. test/. --ext .js,.jsx .","build":"npm run copy && npm run babel","test":"npm run build && npm run eslint && npm run mocha","test:es6":"npm run mocha:es6","cover":"node_modules/istanbul/lib/cli.js cover node_modules/mocha/bin/_mocha -- --reporter spec test/*","watch":"npm run copy && npm run babel:watch","git:push":"npm run build && git push origin && git push origin --tags","npm:patch":"npm version patch && npm publish","npm:minor":"npm version minor && npm publish","npm:major":"npm version major && npm publish","npm:updates":"npm-check-updates"},"repository":{"type":"git","url":"git+https://github.com/eddyystop/feathers-hooks-common.git"},"keywords":["feathers","feathersjs","hook","hooks"],"author":{"name":"John Szwaronek","email":"johnsz9999@gmail.com"},"license":"MIT","bugs":{"url":"https://github.com/eddyystop/feathers-hooks-common/issues"},"homepage":"https://github.com/eddyystop/feathers-hooks-common#readme","dependencies":{"debug":"^2.2.0","feathers-hooks-utils":"^0.1.1","object.assign":"^4.0.4"},"devDependencies":{"babel-cli":"^6.10.1","babel-core":"^6.10.4","babel-eslint":"6.1.0","babel-plugin-add-module-exports":"^0.2.1","babel-preset-es2015":"^6.9.0","chai":"3.5.0","coveralls":"2.11.9","eslint":"3.0.1","eslint-config-airbnb":"9.0.1","eslint-plugin-import":"1.10.2","eslint-plugin-jsx-a11y":"1.5.5","eslint-plugin-react":"5.2.2","istanbul":"0.4.4","mocha":"2.5.3"},"engines":{"node":">=5.0.0","npm":">=3.8.0"},"gitHead":"bd12728abb5f960b5ac2f15647072977a47fce87","_id":"feathers-hooks-common@1.0.0","_shasum":"b450a82cefe0019c787098e225ec65e1210e6cd1","_from":".","_npmVersion":"3.10.5","_nodeVersion":"6.2.2","_npmUser":{"name":"eddystop","email":"johnsz9999@gmail.com"},"dist":{"shasum":"b450a82cefe0019c787098e225ec65e1210e6cd1","tarball":"https://registry.npmjs.org/feathers-hooks-common/-/feathers-hooks-common-1.0.0.tgz"},"maintainers":[{"name":"eddystop","email":"johnsz9999@gmail.com"}],"_npmOperationalInternal":{"host":"packages-12-west.internal.npmjs.com","tmp":"tmp/feathers-hooks-common-1.0.0.tgz_1469458131335_0.7127317003905773"}},"1.0.1":{"name":"feathers-hooks-common","version":"1.0.1","description":"Useful hooks for use with Feathersjs services.","main":"lib/","directories":{"lib":"lib"},"scripts":{"copy":"rm -rf lib/ && cp -r src/ lib/","babel":"babel src/ --out-dir lib --presets babel-preset-es2015","babel:watch":"babel src/ --watch --out-dir lib --presets babel-preset-es2015","mocha":"mocha test/  --reporter spec --compilers js:babel-core/register","mocha:es6":"mocha test/ --reporter spec","eslint":"eslint src/. test/. --ext .js,.jsx .","build":"npm run copy && npm run babel","test":"npm run build && npm run eslint && npm run mocha","test:es6":"npm run mocha:es6","cover":"node_modules/istanbul/lib/cli.js cover node_modules/mocha/bin/_mocha -- --reporter spec test/*","watch":"npm run copy && npm run babel:watch","git:push":"npm run build && git push origin && git push origin --tags","npm:patch":"npm version patch && npm publish","npm:minor":"npm version minor && npm publish","npm:major":"npm version major && npm publish","npm:updates":"npm-check-updates"},"repository":{"type":"git","url":"git+https://github.com/eddyystop/feathers-hooks-common.git"},"keywords":["feathers","feathersjs","hook","hooks"],"author":{"name":"John Szwaronek","email":"johnsz9999@gmail.com"},"license":"MIT","bugs":{"url":"https://github.com/eddyystop/feathers-hooks-common/issues"},"homepage":"https://github.com/eddyystop/feathers-hooks-common#readme","dependencies":{"debug":"^2.2.0","feathers-hooks-utils":"^0.1.1","object.assign":"^4.0.4"},"devDependencies":{"babel-cli":"^6.10.1","babel-core":"^6.10.4","babel-eslint":"6.1.0","babel-plugin-add-module-exports":"^0.2.1","babel-preset-es2015":"^6.9.0","chai":"3.5.0","coveralls":"2.11.9","eslint":"3.0.1","eslint-config-airbnb":"9.0.1","eslint-plugin-import":"1.10.2","eslint-plugin-jsx-a11y":"1.5.5","eslint-plugin-react":"5.2.2","istanbul":"0.4.4","mocha":"2.5.3"},"engines":{"node":">=5.0.0","npm":">=3.8.0"},"gitHead":"c18a644c90cf60cde79165ea521aa6ff658d910b","_id":"feathers-hooks-common@1.0.1","_shasum":"1ded3c8aadbd940871bec156a8b874733cfe4088","_from":".","_npmVersion":"3.10.5","_nodeVersion":"6.2.2","_npmUser":{"name":"eddystop","email":"johnsz9999@gmail.com"},"dist":{"shasum":"1ded3c8aadbd940871bec156a8b874733cfe4088","tarball":"https://registry.npmjs.org/feathers-hooks-common/-/feathers-hooks-common-1.0.1.tgz"},"maintainers":[{"name":"eddystop","email":"johnsz9999@gmail.com"}],"_npmOperationalInternal":{"host":"packages-16-east.internal.npmjs.com","tmp":"tmp/feathers-hooks-common-1.0.1.tgz_1469460900457_0.640969596337527"}},"1.1.0":{"name":"feathers-hooks-common","version":"1.1.0","description":"Useful hooks for use with Feathersjs services.","main":"lib/","directories":{"lib":"lib"},"scripts":{"copy":"rm -rf lib/ && cp -r src/ lib/","babel":"babel src/ --out-dir lib --presets babel-preset-es2015","babel:watch":"babel src/ --watch --out-dir lib --presets babel-preset-es2015","mocha":"mocha test/  --reporter spec --compilers js:babel-core/register","mocha:only":"mocha test/ --reporter spec","eslint":"eslint src/. test/. --ext .js,.jsx","build":"npm run copy && npm run babel","test":"npm run eslint && npm run build &&  npm run mocha","test:build":"npm run build && npm run mocha:only","test:only":"npm run mocha:only","cover":"node_modules/istanbul/lib/cli.js cover node_modules/mocha/bin/_mocha -- --reporter spec test/*","watch":"npm run copy && npm run babel:watch","npm:patch":"npm version patch && npm publish","npm:minor":"npm version minor && npm publish","npm:major":"npm version major && npm publish","npm:updates":"npm-check-updates"},"repository":{"type":"git","url":"git+https://github.com/eddyystop/feathers-hooks-common.git"},"keywords":["feathers","feathersjs","hook","hooks"],"author":{"name":"John Szwaronek","email":"johnsz9999@gmail.com"},"license":"MIT","bugs":{"url":"https://github.com/eddyystop/feathers-hooks-common/issues"},"homepage":"https://github.com/eddyystop/feathers-hooks-common#readme","dependencies":{"debug":"^2.2.0","feathers-hooks-utils":"^0.1.1","object.assign":"^4.0.4"},"devDependencies":{"babel-cli":"^6.10.1","babel-core":"^6.10.4","babel-eslint":"6.1.0","babel-plugin-add-module-exports":"^0.2.1","babel-preset-es2015":"^6.9.0","chai":"3.5.0","coveralls":"2.11.9","eslint":"3.0.1","eslint-config-airbnb":"9.0.1","eslint-plugin-import":"1.10.2","eslint-plugin-jsdoc":"2.3.1","eslint-plugin-jsx-a11y":"1.5.5","eslint-plugin-react":"5.2.2","feathers-tests-fake-app-users":"1.0.0","istanbul":"0.4.4","mocha":"2.5.3"},"engines":{"node":">=5.0.0","npm":">=3.8.0"},"gitHead":"f5ec3cc0635662b53dd9455e4ecb49aa6eb3f095","_id":"feathers-hooks-common@1.1.0","_shasum":"5bd424d86c92e064a3b4fa183a0103cc224f69cc","_from":".","_npmVersion":"3.10.5","_nodeVersion":"6.2.2","_npmUser":{"name":"eddystop","email":"johnsz9999@gmail.com"},"dist":{"shasum":"5bd424d86c92e064a3b4fa183a0103cc224f69cc","tarball":"https://registry.npmjs.org/feathers-hooks-common/-/feathers-hooks-common-1.1.0.tgz"},"maintainers":[{"name":"eddystop","email":"johnsz9999@gmail.com"}],"_npmOperationalInternal":{"host":"packages-12-west.internal.npmjs.com","tmp":"tmp/feathers-hooks-common-1.1.0.tgz_1471463103184_0.06596967880614102"}},"1.1.1":{"name":"feathers-hooks-common","version":"1.1.1","description":"Useful hooks for use with Feathersjs services.","main":"lib/","directories":{"lib":"lib"},"scripts":{"copy":"rm -rf lib/ && cp -r src/ lib/","babel":"babel src/ --out-dir lib --presets babel-preset-es2015","babel:watch":"babel src/ --watch --out-dir lib --presets babel-preset-es2015","mocha":"mocha test/  --reporter spec --compilers js:babel-core/register","mocha:only":"mocha test/ --reporter spec","eslint":"eslint src/. test/. --ext .js,.jsx","build":"npm run copy && npm run babel","test":"npm run eslint && npm run build &&  npm run mocha","test:build":"npm run build && npm run mocha:only","test:only":"npm run mocha:only","cover":"node_modules/istanbul/lib/cli.js cover node_modules/mocha/bin/_mocha -- --reporter spec test/*","watch":"npm run copy && npm run babel:watch","npm:patch":"npm version patch && npm publish","npm:minor":"npm version minor && npm publish","npm:major":"npm version major && npm publish","npm:updates":"npm-check-updates"},"repository":{"type":"git","url":"git+https://github.com/eddyystop/feathers-hooks-common.git"},"keywords":["feathers","feathersjs","hook","hooks"],"author":{"name":"John Szwaronek","email":"johnsz9999@gmail.com"},"license":"MIT","bugs":{"url":"https://github.com/eddyystop/feathers-hooks-common/issues"},"homepage":"https://github.com/eddyystop/feathers-hooks-common#readme","dependencies":{"debug":"^2.2.0","feathers-hooks-utils":"^0.1.1","object.assign":"^4.0.4"},"devDependencies":{"babel-cli":"^6.10.1","babel-core":"^6.10.4","babel-eslint":"6.1.0","babel-plugin-add-module-exports":"^0.2.1","babel-preset-es2015":"^6.9.0","chai":"3.5.0","coveralls":"2.11.9","eslint":"3.0.1","eslint-config-airbnb":"9.0.1","eslint-plugin-import":"1.10.2","eslint-plugin-jsdoc":"2.3.1","eslint-plugin-jsx-a11y":"1.5.5","eslint-plugin-react":"5.2.2","feathers-tests-fake-app-users":"1.0.0","istanbul":"0.4.4","mocha":"2.5.3"},"engines":{"node":">=5.0.0","npm":">=3.8.0"},"gitHead":"1089635f91957f037a90418e1ecca9da4391519a","_id":"feathers-hooks-common@1.1.1","_shasum":"84815a700a0bb296e6ab8f889b54fd343ce56f40","_from":".","_npmVersion":"3.10.5","_nodeVersion":"6.2.2","_npmUser":{"name":"eddystop","email":"johnsz9999@gmail.com"},"dist":{"shasum":"84815a700a0bb296e6ab8f889b54fd343ce56f40","tarball":"https://registry.npmjs.org/feathers-hooks-common/-/feathers-hooks-common-1.1.1.tgz"},"maintainers":[{"name":"eddystop","email":"johnsz9999@gmail.com"}],"_npmOperationalInternal":{"host":"packages-16-east.internal.npmjs.com","tmp":"tmp/feathers-hooks-common-1.1.1.tgz_1471463710363_0.085609195753932"}},"1.2.0":{"name":"feathers-hooks-common","version":"1.2.0","description":"Useful hooks for use with Feathersjs services.","main":"lib/","directories":{"lib":"lib"},"scripts":{"copy":"rm -rf lib/ && cp -r src/ lib/","babel":"babel src/ --out-dir lib --presets babel-preset-es2015","babel:watch":"babel src/ --watch --out-dir lib --presets babel-preset-es2015","mocha":"mocha test/  --reporter spec --compilers js:babel-core/register","mocha:only":"mocha test/ --reporter spec","eslint":"eslint src/. test/. --ext .js,.jsx","build":"npm run copy && npm run babel","test":"npm run eslint && npm run build &&  npm run mocha","test:build":"npm run build && npm run mocha:only","test:only":"npm run mocha:only","cover":"node_modules/istanbul/lib/cli.js cover node_modules/mocha/bin/_mocha -- --reporter spec test/*","watch":"npm run copy && npm run babel:watch","npm:patch":"npm version patch && npm publish","npm:minor":"npm version minor && npm publish","npm:major":"npm version major && npm publish","npm:updates":"npm-check-updates"},"repository":{"type":"git","url":"git+https://github.com/eddyystop/feathers-hooks-common.git"},"keywords":["feathers","feathersjs","hook","hooks"],"author":{"name":"John Szwaronek","email":"johnsz9999@gmail.com"},"license":"MIT","bugs":{"url":"https://github.com/eddyystop/feathers-hooks-common/issues"},"homepage":"https://github.com/eddyystop/feathers-hooks-common#readme","dependencies":{"debug":"^2.2.0","feathers-hooks-utils":"^0.1.1","object.assign":"^4.0.4"},"devDependencies":{"babel-cli":"^6.10.1","babel-core":"^6.10.4","babel-eslint":"6.1.0","babel-plugin-add-module-exports":"^0.2.1","babel-preset-es2015":"^6.9.0","chai":"3.5.0","coveralls":"2.11.9","eslint":"3.0.1","eslint-config-airbnb":"9.0.1","eslint-plugin-import":"1.10.2","eslint-plugin-jsdoc":"2.3.1","eslint-plugin-jsx-a11y":"1.5.5","eslint-plugin-react":"5.2.2","feathers-tests-fake-app-users":"1.0.0","istanbul":"0.4.4","mocha":"2.5.3"},"engines":{"node":">=5.0.0","npm":">=3.8.0"},"gitHead":"f46d0584719ce01147ccedb252f2689ed58cbc8e","_id":"feathers-hooks-common@1.2.0","_shasum":"543f7da5715b831c44e089ddad980cb5bd75b84c","_from":".","_npmVersion":"3.10.5","_nodeVersion":"6.2.2","_npmUser":{"name":"eddystop","email":"johnsz9999@gmail.com"},"dist":{"shasum":"543f7da5715b831c44e089ddad980cb5bd75b84c","tarball":"https://registry.npmjs.org/feathers-hooks-common/-/feathers-hooks-common-1.2.0.tgz"},"maintainers":[{"name":"eddystop","email":"johnsz9999@gmail.com"}],"_npmOperationalInternal":{"host":"packages-12-west.internal.npmjs.com","tmp":"tmp/feathers-hooks-common-1.2.0.tgz_1471533890487_0.4868353442288935"}},"1.2.1":{"name":"feathers-hooks-common","version":"1.2.1","description":"Useful hooks for use with Feathersjs services.","main":"lib/","directories":{"lib":"lib"},"scripts":{"copy":"rm -rf lib/ && cp -r src/ lib/","babel":"babel src/ --out-dir lib --presets babel-preset-es2015","babel:watch":"babel src/ --watch --out-dir lib --presets babel-preset-es2015","mocha":"mocha test/  --reporter spec --compilers js:babel-core/register","mocha:only":"mocha test/ --reporter spec","eslint":"eslint src/. test/. --ext .js,.jsx","build":"npm run copy && npm run babel","test":"npm run eslint && npm run build &&  npm run mocha","test:build":"npm run build && npm run mocha:only","test:only":"npm run mocha:only","cover":"node_modules/istanbul/lib/cli.js cover node_modules/mocha/bin/_mocha -- --reporter spec test/*","watch":"npm run copy && npm run babel:watch","npm:patch":"npm version patch && npm publish","npm:minor":"npm version minor && npm publish","npm:major":"npm version major && npm publish","npm:updates":"npm-check-updates"},"repository":{"type":"git","url":"git+https://github.com/eddyystop/feathers-hooks-common.git"},"keywords":["feathers","feathersjs","hook","hooks"],"author":{"name":"John Szwaronek","email":"johnsz9999@gmail.com"},"license":"MIT","bugs":{"url":"https://github.com/eddyystop/feathers-hooks-common/issues"},"homepage":"https://github.com/eddyystop/feathers-hooks-common#readme","dependencies":{"debug":"^2.2.0","feathers-hooks-utils":"^0.1.1","object.assign":"^4.0.4"},"devDependencies":{"babel-cli":"^6.10.1","babel-core":"^6.10.4","babel-eslint":"6.1.0","babel-plugin-add-module-exports":"^0.2.1","babel-preset-es2015":"^6.9.0","chai":"3.5.0","coveralls":"2.11.9","eslint":"3.0.1","eslint-config-airbnb":"9.0.1","eslint-plugin-import":"1.10.2","eslint-plugin-jsdoc":"2.3.1","eslint-plugin-jsx-a11y":"1.5.5","eslint-plugin-react":"5.2.2","feathers-tests-fake-app-users":"1.0.0","istanbul":"0.4.4","mocha":"2.5.3"},"engines":{"node":">=5.0.0","npm":">=3.8.0"},"gitHead":"2098be8aa48ff96818f47c91a6811da3df6bc8b1","_id":"feathers-hooks-common@1.2.1","_shasum":"e02ed7203c39201e44b74a0dcd4cc0af1fda822e","_from":".","_npmVersion":"3.10.5","_nodeVersion":"6.2.2","_npmUser":{"name":"eddystop","email":"johnsz9999@gmail.com"},"dist":{"shasum":"e02ed7203c39201e44b74a0dcd4cc0af1fda822e","tarball":"https://registry.npmjs.org/feathers-hooks-common/-/feathers-hooks-common-1.2.1.tgz"},"maintainers":[{"name":"eddystop","email":"johnsz9999@gmail.com"}],"_npmOperationalInternal":{"host":"packages-16-east.internal.npmjs.com","tmp":"tmp/feathers-hooks-common-1.2.1.tgz_1471537103379_0.45475442986935377"}},"1.2.2":{"name":"feathers-hooks-common","version":"1.2.2","description":"Useful hooks for use with Feathersjs services.","main":"lib/","directories":{"lib":"lib"},"scripts":{"copy":"rm -rf lib/ && cp -r src/ lib/","babel":"babel src/ --out-dir lib --presets babel-preset-es2015","babel:watch":"babel src/ --watch --out-dir lib --presets babel-preset-es2015","mocha":"mocha test/  --reporter spec --compilers js:babel-core/register","mocha:only":"mocha test/ --reporter spec","eslint":"eslint src/. test/. --ext .js,.jsx","build":"npm run copy && npm run babel","test":"npm run eslint && npm run build &&  npm run mocha","test:build":"npm run build && npm run mocha:only","test:only":"npm run mocha:only","cover":"node_modules/istanbul/lib/cli.js cover node_modules/mocha/bin/_mocha -- --reporter spec test/*","watch":"npm run copy && npm run babel:watch","npm:patch":"npm version patch && npm publish","npm:minor":"npm version minor && npm publish","npm:major":"npm version major && npm publish","npm:updates":"npm-check-updates"},"repository":{"type":"git","url":"git+https://github.com/eddyystop/feathers-hooks-common.git"},"keywords":["feathers","feathersjs","hook","hooks"],"author":{"name":"John Szwaronek","email":"johnsz9999@gmail.com"},"license":"MIT","bugs":{"url":"https://github.com/eddyystop/feathers-hooks-common/issues"},"homepage":"https://github.com/eddyystop/feathers-hooks-common#readme","dependencies":{"debug":"^2.2.0","feathers-hooks-utils":"^0.1.1","object.assign":"^4.0.4"},"devDependencies":{"babel-cli":"^6.10.1","babel-core":"^6.10.4","babel-eslint":"6.1.0","babel-plugin-add-module-exports":"^0.2.1","babel-preset-es2015":"^6.9.0","chai":"3.5.0","coveralls":"2.11.9","eslint":"3.0.1","eslint-config-airbnb":"9.0.1","eslint-plugin-import":"1.10.2","eslint-plugin-jsdoc":"2.3.1","eslint-plugin-jsx-a11y":"1.5.5","eslint-plugin-react":"5.2.2","feathers-tests-fake-app-users":"1.0.0","istanbul":"0.4.4","mocha":"2.5.3"},"engines":{"node":">=5.0.0","npm":">=3.8.0"},"gitHead":"fb5958af4d938752b6cc1a0497fd10f299af089d","_id":"feathers-hooks-common@1.2.2","_shasum":"c9ff90e5f954bb1343f47a32aa1f5b95665b0d92","_from":".","_npmVersion":"3.10.5","_nodeVersion":"6.2.2","_npmUser":{"name":"eddystop","email":"johnsz9999@gmail.com"},"dist":{"shasum":"c9ff90e5f954bb1343f47a32aa1f5b95665b0d92","tarball":"https://registry.npmjs.org/feathers-hooks-common/-/feathers-hooks-common-1.2.2.tgz"},"maintainers":[{"name":"eddystop","email":"johnsz9999@gmail.com"}],"_npmOperationalInternal":{"host":"packages-12-west.internal.npmjs.com","tmp":"tmp/feathers-hooks-common-1.2.2.tgz_1471537964876_0.09366444637998939"}},"1.3.0":{"name":"feathers-hooks-common","version":"1.3.0","description":"Useful hooks for use with Feathersjs services.","main":"lib/","directories":{"lib":"lib"},"scripts":{"copy":"rm -rf lib/ && cp -r src/ lib/","babel":"babel src/ --out-dir lib --presets babel-preset-es2015","babel:watch":"babel src/ --watch --out-dir lib --presets babel-preset-es2015","mocha":"mocha test/  --reporter spec --compilers js:babel-core/register","mocha:only":"mocha test/ --reporter spec","eslint":"eslint src/. test/. --ext .js,.jsx","build":"npm run copy && npm run babel","test":"npm run build && npm run eslint && npm run mocha","test:build":"npm run build && npm run mocha:only","test:only":"npm run mocha:only","cover":"node_modules/istanbul/lib/cli.js cover node_modules/mocha/bin/_mocha -- --reporter spec test/*","watch":"npm run copy && npm run babel:watch","npm:patch":"npm version patch && npm publish","npm:minor":"npm version minor && npm publish","npm:major":"npm version major && npm publish","npm:updates":"npm-check-updates"},"repository":{"type":"git","url":"git+https://github.com/eddyystop/feathers-hooks-common.git"},"keywords":["feathers","feathersjs","hook","hooks"],"author":{"name":"John Szwaronek","email":"johnsz9999@gmail.com"},"license":"MIT","bugs":{"url":"https://github.com/eddyystop/feathers-hooks-common/issues"},"homepage":"https://github.com/eddyystop/feathers-hooks-common#readme","dependencies":{"debug":"^2.2.0","feathers-hooks-utils":"^0.1.1","object.assign":"^4.0.4"},"devDependencies":{"babel-cli":"^6.10.1","babel-core":"^6.10.4","babel-eslint":"6.1.0","babel-plugin-add-module-exports":"^0.2.1","babel-preset-es2015":"^6.9.0","chai":"3.5.0","coveralls":"2.11.9","eslint":"3.0.1","eslint-config-airbnb":"9.0.1","eslint-plugin-import":"1.10.2","eslint-plugin-jsdoc":"2.3.1","eslint-plugin-jsx-a11y":"1.5.5","eslint-plugin-react":"5.2.2","feathers-tests-fake-app-users":"1.0.0","istanbul":"0.4.4","mocha":"2.5.3"},"engines":{"node":">=5.0.0","npm":">=3.8.0"},"gitHead":"e3906858b656646094eecea9781ef932a68b11b1","_id":"feathers-hooks-common@1.3.0","_shasum":"54e48e90520b6082fffe9839af509714e323aabe","_from":".","_npmVersion":"3.10.5","_nodeVersion":"6.2.2","_npmUser":{"name":"eddystop","email":"johnsz9999@gmail.com"},"dist":{"shasum":"54e48e90520b6082fffe9839af509714e323aabe","tarball":"https://registry.npmjs.org/feathers-hooks-common/-/feathers-hooks-common-1.3.0.tgz"},"maintainers":[{"name":"eddystop","email":"johnsz9999@gmail.com"}],"_npmOperationalInternal":{"host":"packages-12-west.internal.npmjs.com","tmp":"tmp/feathers-hooks-common-1.3.0.tgz_1471547319264_0.6862954755779356"}},"1.3.1":{"name":"feathers-hooks-common","version":"1.3.1","description":"Useful hooks for use with Feathersjs services.","main":"lib/","directories":{"lib":"lib"},"scripts":{"copy":"rm -rf lib/ && cp -r src/ lib/","babel":"babel src/ --out-dir lib --presets babel-preset-es2015","babel:watch":"babel src/ --watch --out-dir lib --presets babel-preset-es2015","mocha":"mocha test/  --reporter spec --compilers js:babel-core/register","mocha:only":"mocha test/ --reporter spec","eslint":"eslint src/. test/. --ext .js,.jsx","build":"npm run copy && npm run babel","test":"npm run build && npm run eslint && npm run mocha","test:build":"npm run build && npm run mocha:only","test:only":"npm run mocha:only","cover":"node_modules/istanbul/lib/cli.js cover node_modules/mocha/bin/_mocha -- --reporter spec test/*","watch":"npm run copy && npm run babel:watch","npm:patch":"npm version patch && npm publish","npm:minor":"npm version minor && npm publish","npm:major":"npm version major && npm publish","npm:updates":"npm-check-updates"},"repository":{"type":"git","url":"git+https://github.com/feathersjs/feathers-hooks-common.git"},"keywords":["feathers","feathersjs","hook","hooks"],"author":{"name":"John Szwaronek","email":"johnsz9999@gmail.com"},"license":"MIT","bugs":{"url":"https://github.com/feathersjs/feathers-hooks-common/issues"},"homepage":"https://github.com/feathers/feathers-hooks-common#readme","dependencies":{"debug":"^2.2.0","feathers-hooks-utils":"^0.1.1","object.assign":"^4.0.4"},"devDependencies":{"babel-cli":"^6.10.1","babel-core":"^6.10.4","babel-eslint":"6.1.0","babel-plugin-add-module-exports":"^0.2.1","babel-preset-es2015":"^6.9.0","chai":"3.5.0","coveralls":"2.11.9","eslint":"3.0.1","eslint-config-airbnb":"9.0.1","eslint-plugin-import":"1.10.2","eslint-plugin-jsdoc":"2.3.1","eslint-plugin-jsx-a11y":"1.5.5","eslint-plugin-react":"5.2.2","feathers-tests-fake-app-users":"1.0.0","istanbul":"0.4.4","mocha":"2.5.3"},"engines":{"node":">=5.0.0","npm":">=3.8.0"},"gitHead":"ca85f641119431826216e9a32b0b87eb9964f15f","_id":"feathers-hooks-common@1.3.1","_shasum":"7921266ac4ba626dfc93ed93d6d3ea4cb2908444","_from":".","_npmVersion":"3.10.5","_nodeVersion":"6.2.2","_npmUser":{"name":"eddystop","email":"johnsz9999@gmail.com"},"dist":{"shasum":"7921266ac4ba626dfc93ed93d6d3ea4cb2908444","tarball":"https://registry.npmjs.org/feathers-hooks-common/-/feathers-hooks-common-1.3.1.tgz"},"maintainers":[{"name":"eddystop","email":"johnsz9999@gmail.com"}],"_npmOperationalInternal":{"host":"packages-16-east.internal.npmjs.com","tmp":"tmp/feathers-hooks-common-1.3.1.tgz_1471548275769_0.03863420244306326"}},"1.4.0":{"name":"feathers-hooks-common","version":"1.4.0","description":"Useful hooks for use with Feathersjs services.","main":"lib/","directories":{"lib":"lib"},"scripts":{"copy":"rm -rf lib/ && cp -r src/ lib/","babel":"babel src/ --out-dir lib --presets babel-preset-es2015","babel:watch":"babel src/ --watch --out-dir lib --presets babel-preset-es2015","mocha":"mocha test/  --reporter spec --compilers js:babel-core/register","mocha:only":"mocha test/ --reporter spec","eslint":"eslint src/. test/. --ext .js,.jsx","build":"npm run copy && npm run babel","test":"npm run build && npm run eslint && npm run mocha","test:build":"npm run build && npm run mocha:only","test:only":"npm run mocha:only","cover":"node_modules/istanbul/lib/cli.js cover node_modules/mocha/bin/_mocha -- --reporter spec test/*","watch":"npm run copy && npm run babel:watch","npm:patch":"npm version patch && npm publish","npm:minor":"npm version minor && npm publish","npm:major":"npm version major && npm publish","npm:updates":"npm-check-updates"},"repository":{"type":"git","url":"git+https://github.com/feathersjs/feathers-hooks-common.git"},"keywords":["feathers","feathersjs","hook","hooks"],"author":{"name":"John Szwaronek","email":"johnsz9999@gmail.com"},"license":"MIT","bugs":{"url":"https://github.com/feathersjs/feathers-hooks-common/issues"},"homepage":"https://github.com/feathers/feathers-hooks-common#readme","dependencies":{"debug":"^2.2.0","feathers-hooks-utils":"^0.1.1","object.assign":"^4.0.4"},"devDependencies":{"babel-cli":"^6.10.1","babel-core":"^6.10.4","babel-eslint":"6.1.0","babel-plugin-add-module-exports":"^0.2.1","babel-preset-es2015":"^6.9.0","chai":"3.5.0","coveralls":"2.11.9","eslint":"3.0.1","eslint-config-airbnb":"9.0.1","eslint-plugin-import":"1.10.2","eslint-plugin-jsdoc":"2.3.1","eslint-plugin-jsx-a11y":"1.5.5","eslint-plugin-react":"5.2.2","feathers-tests-fake-app-users":"1.0.0","istanbul":"0.4.4","mocha":"2.5.3"},"engines":{"node":">=5.0.0","npm":">=3.8.0"},"gitHead":"d1ac82e51a461fe90cfd86367faf66efc6671549","_id":"feathers-hooks-common@1.4.0","_shasum":"03bd108883c4c043c28ecefd72ed7a68aaae18b0","_from":".","_npmVersion":"3.10.5","_nodeVersion":"6.2.2","_npmUser":{"name":"eddystop","email":"johnsz9999@gmail.com"},"dist":{"shasum":"03bd108883c4c043c28ecefd72ed7a68aaae18b0","tarball":"https://registry.npmjs.org/feathers-hooks-common/-/feathers-hooks-common-1.4.0.tgz"},"maintainers":[{"name":"eddystop","email":"johnsz9999@gmail.com"}],"_npmOperationalInternal":{"host":"packages-12-west.internal.npmjs.com","tmp":"tmp/feathers-hooks-common-1.4.0.tgz_1471636994401_0.7521304846741259"}},"1.4.1":{"name":"feathers-hooks-common","version":"1.4.1","description":"Useful hooks for use with Feathersjs services.","main":"lib/","directories":{"lib":"lib"},"scripts":{"copy":"rm -rf lib/ && cp -r src/ lib/","babel":"babel src/ --out-dir lib --presets babel-preset-es2015","babel:watch":"babel src/ --watch --out-dir lib --presets babel-preset-es2015","mocha":"mocha test/  --reporter spec --compilers js:babel-core/register","mocha:only":"mocha test/ --reporter spec","eslint":"eslint src/. test/. --ext .js,.jsx","build":"npm run copy && npm run babel","test":"npm run build && npm run eslint && npm run mocha","test:build":"npm run build && npm run mocha:only","test:only":"npm run mocha:only","cover":"node_modules/istanbul/lib/cli.js cover node_modules/mocha/bin/_mocha -- --reporter spec test/*","watch":"npm run copy && npm run babel:watch","npm:patch":"npm version patch && npm publish","npm:minor":"npm version minor && npm publish","npm:major":"npm version major && npm publish","npm:updates":"npm-check-updates"},"repository":{"type":"git","url":"git+https://github.com/feathersjs/feathers-hooks-common.git"},"keywords":["feathers","feathersjs","hook","hooks"],"author":{"name":"John Szwaronek","email":"johnsz9999@gmail.com"},"license":"MIT","bugs":{"url":"https://github.com/feathersjs/feathers-hooks-common/issues"},"homepage":"https://github.com/feathers/feathers-hooks-common#readme","dependencies":{"debug":"^2.2.0","feathers-hooks-utils":"^0.1.1","object.assign":"^4.0.4"},"devDependencies":{"babel-cli":"^6.10.1","babel-core":"^6.10.4","babel-eslint":"6.1.0","babel-plugin-add-module-exports":"^0.2.1","babel-preset-es2015":"^6.9.0","chai":"3.5.0","coveralls":"2.11.9","eslint":"3.0.1","eslint-config-airbnb":"9.0.1","eslint-plugin-import":"1.10.2","eslint-plugin-jsdoc":"2.3.1","eslint-plugin-jsx-a11y":"1.5.5","eslint-plugin-react":"5.2.2","feathers-tests-fake-app-users":"1.0.0","istanbul":"0.4.4","mocha":"2.5.3"},"engines":{"node":">=5.0.0","npm":">=3.8.0"},"gitHead":"319c944950c62a61b4084b67d4fa149ab18500bb","_id":"feathers-hooks-common@1.4.1","_shasum":"1efe45c8e41921df658cbc02a25d9502ae4bc6ad","_from":".","_npmVersion":"3.10.5","_nodeVersion":"6.2.2","_npmUser":{"name":"eddystop","email":"johnsz9999@gmail.com"},"dist":{"shasum":"1efe45c8e41921df658cbc02a25d9502ae4bc6ad","tarball":"https://registry.npmjs.org/feathers-hooks-common/-/feathers-hooks-common-1.4.1.tgz"},"maintainers":[{"name":"eddystop","email":"johnsz9999@gmail.com"}],"_npmOperationalInternal":{"host":"packages-16-east.internal.npmjs.com","tmp":"tmp/feathers-hooks-common-1.4.1.tgz_1471637365858_0.11752773355692625"}},"1.5.0":{"name":"feathers-hooks-common","version":"1.5.0","description":"Useful hooks for use with Feathersjs services.","main":"lib/","directories":{"lib":"lib"},"scripts":{"copy":"rm -rf lib/ && cp -r src/ lib/","babel":"babel src/ --out-dir lib --presets babel-preset-es2015","babel:watch":"babel src/ --watch --out-dir lib --presets babel-preset-es2015","mocha":"mocha test/  --reporter spec --compilers js:babel-core/register","mocha:only":"mocha test/ --reporter spec","eslint":"eslint src/. test/. --ext .js,.jsx","build":"npm run copy && npm run babel","test":"npm run build && npm run eslint && npm run mocha","test:build":"npm run build && npm run mocha:only","test:only":"npm run mocha:only","cover":"node_modules/istanbul/lib/cli.js cover node_modules/mocha/bin/_mocha -- --reporter spec test/*","watch":"npm run copy && npm run babel:watch","npm:patch":"npm version patch && npm publish","npm:minor":"npm version minor && npm publish","npm:major":"npm version major && npm publish","npm:updates":"npm-check-updates"},"repository":{"type":"git","url":"git+https://github.com/feathersjs/feathers-hooks-common.git"},"keywords":["feathers","feathersjs","hook","hooks"],"author":{"name":"John Szwaronek","email":"johnsz9999@gmail.com"},"license":"MIT","bugs":{"url":"https://github.com/feathersjs/feathers-hooks-common/issues"},"homepage":"https://github.com/feathers/feathers-hooks-common#readme","dependencies":{"debug":"^2.2.0","feathers-hooks-utils":"^0.1.1","object.assign":"^4.0.4"},"devDependencies":{"babel-cli":"^6.10.1","babel-core":"^6.10.4","babel-eslint":"6.1.0","babel-plugin-add-module-exports":"^0.2.1","babel-preset-es2015":"^6.9.0","chai":"3.5.0","coveralls":"2.11.9","eslint":"3.0.1","eslint-config-airbnb":"9.0.1","eslint-plugin-import":"1.10.2","eslint-plugin-jsdoc":"2.3.1","eslint-plugin-jsx-a11y":"1.5.5","eslint-plugin-react":"5.2.2","feathers-tests-fake-app-users":"1.0.0","istanbul":"0.4.4","mocha":"2.5.3"},"engines":{"node":">=5.0.0","npm":">=3.8.0"},"gitHead":"1e173d4141af91154aabe016188408161dc51093","_id":"feathers-hooks-common@1.5.0","_shasum":"e75547f0932ccf1215afb7d8549bda81dfe6f406","_from":".","_npmVersion":"3.10.5","_nodeVersion":"6.2.2","_npmUser":{"name":"eddystop","email":"johnsz9999@gmail.com"},"dist":{"shasum":"e75547f0932ccf1215afb7d8549bda81dfe6f406","tarball":"https://registry.npmjs.org/feathers-hooks-common/-/feathers-hooks-common-1.5.0.tgz"},"maintainers":[{"name":"daffl","email":"daff@neyeon.de"},{"name":"eddystop","email":"johnsz9999@gmail.com"},{"name":"ekryski","email":"e.kryski@gmail.com"}],"_npmOperationalInternal":{"host":"packages-12-west.internal.npmjs.com","tmp":"tmp/feathers-hooks-common-1.5.0.tgz_1471716480997_0.1291971846949309"}},"1.5.1":{"name":"feathers-hooks-common","version":"1.5.1","description":"Useful hooks for use with Feathersjs services.","main":"lib/","directories":{"lib":"lib"},"scripts":{"copy":"rm -rf lib/ && cp -r src/ lib/","babel":"babel src/ --out-dir lib --presets babel-preset-es2015","babel:watch":"babel src/ --watch --out-dir lib --presets babel-preset-es2015","mocha":"mocha test/  --reporter spec --compilers js:babel-core/register","mocha:only":"mocha test/ --reporter spec","eslint":"eslint src/. test/. --ext .js,.jsx","build":"npm run copy && npm run babel","test":"npm run build && npm run eslint && npm run mocha","test:build":"npm run build && npm run mocha:only","test:only":"npm run mocha:only","cover":"node_modules/istanbul/lib/cli.js cover node_modules/mocha/bin/_mocha -- --reporter spec test/*","watch":"npm run copy && npm run babel:watch","npm:patch":"npm version patch && npm publish","npm:minor":"npm version minor && npm publish","npm:major":"npm version major && npm publish","npm:updates":"npm-check-updates"},"repository":{"type":"git","url":"git+https://github.com/feathersjs/feathers-hooks-common.git"},"keywords":["feathers","feathersjs","hook","hooks"],"author":{"name":"John Szwaronek","email":"johnsz9999@gmail.com"},"license":"MIT","bugs":{"url":"https://github.com/feathersjs/feathers-hooks-common/issues"},"homepage":"https://github.com/feathers/feathers-hooks-common#readme","dependencies":{"debug":"^2.2.0","feathers-hooks-utils":"^0.1.1","object.assign":"^4.0.4"},"devDependencies":{"babel-cli":"^6.10.1","babel-core":"^6.10.4","babel-eslint":"6.1.0","babel-plugin-add-module-exports":"^0.2.1","babel-preset-es2015":"^6.9.0","chai":"3.5.0","coveralls":"2.11.9","eslint":"3.0.1","eslint-config-airbnb":"9.0.1","eslint-plugin-import":"1.10.2","eslint-plugin-jsdoc":"2.3.1","eslint-plugin-jsx-a11y":"1.5.5","eslint-plugin-react":"5.2.2","feathers-tests-fake-app-users":"1.0.0","istanbul":"0.4.4","mocha":"2.5.3"},"engines":{"node":">=5.0.0","npm":">=3.8.0"},"gitHead":"9ca3e67300fb83c699d446bd47158069be842c3a","_id":"feathers-hooks-common@1.5.1","_shasum":"263197b0e3db93be41bf538db8ec156f39412cf4","_from":".","_npmVersion":"3.10.5","_nodeVersion":"6.2.2","_npmUser":{"name":"eddystop","email":"johnsz9999@gmail.com"},"dist":{"shasum":"263197b0e3db93be41bf538db8ec156f39412cf4","tarball":"https://registry.npmjs.org/feathers-hooks-common/-/feathers-hooks-common-1.5.1.tgz"},"maintainers":[{"name":"daffl","email":"daff@neyeon.de"},{"name":"eddystop","email":"johnsz9999@gmail.com"},{"name":"ekryski","email":"e.kryski@gmail.com"}],"_npmOperationalInternal":{"host":"packages-12-west.internal.npmjs.com","tmp":"tmp/feathers-hooks-common-1.5.1.tgz_1471716827569_0.6863485143985599"}},"1.5.2":{"name":"feathers-hooks-common","version":"1.5.2","description":"Useful hooks for use with Feathersjs services.","main":"lib/","directories":{"lib":"lib"},"scripts":{"copy":"rm -rf lib/ && cp -r src/ lib/","babel":"babel src/ --out-dir lib --presets babel-preset-es2015","babel:watch":"babel src/ --watch --out-dir lib --presets babel-preset-es2015","mocha":"mocha test/  --reporter spec --compilers js:babel-core/register","mocha:only":"mocha test/ --reporter spec","eslint":"eslint src/. test/. --ext .js,.jsx","build":"npm run copy && npm run babel","test":"npm run build && npm run eslint && npm run mocha","test:build":"npm run build && npm run mocha:only","test:only":"npm run mocha:only","cover":"node_modules/istanbul/lib/cli.js cover node_modules/mocha/bin/_mocha -- --reporter spec test/*","watch":"npm run copy && npm run babel:watch","npm:patch":"npm version patch && npm publish","npm:minor":"npm version minor && npm publish","npm:major":"npm version major && npm publish","npm:updates":"npm-check-updates"},"repository":{"type":"git","url":"git+https://github.com/feathersjs/feathers-hooks-common.git"},"keywords":["feathers","feathersjs","hook","hooks"],"author":{"name":"John Szwaronek","email":"johnsz9999@gmail.com"},"license":"MIT","bugs":{"url":"https://github.com/feathersjs/feathers-hooks-common/issues"},"homepage":"https://github.com/feathers/feathers-hooks-common#readme","dependencies":{"debug":"^2.2.0","feathers-hooks-utils":"^0.1.1","object.assign":"^4.0.4"},"devDependencies":{"babel-cli":"^6.10.1","babel-core":"^6.10.4","babel-eslint":"6.1.0","babel-plugin-add-module-exports":"^0.2.1","babel-preset-es2015":"^6.9.0","chai":"3.5.0","coveralls":"2.11.9","eslint":"3.0.1","eslint-config-airbnb":"9.0.1","eslint-plugin-import":"1.10.2","eslint-plugin-jsdoc":"2.3.1","eslint-plugin-jsx-a11y":"1.5.5","eslint-plugin-react":"5.2.2","feathers-tests-fake-app-users":"1.0.0","istanbul":"0.4.4","mocha":"2.5.3"},"engines":{"node":">=5.0.0","npm":">=3.8.0"},"gitHead":"cbec5e9f53ff550661f14575aa53bfbb6989792a","_id":"feathers-hooks-common@1.5.2","_shasum":"b64e1dae7178253fa4695d3355193796a6a556eb","_from":".","_npmVersion":"3.10.5","_nodeVersion":"6.2.2","_npmUser":{"name":"eddystop","email":"johnsz9999@gmail.com"},"dist":{"shasum":"b64e1dae7178253fa4695d3355193796a6a556eb","tarball":"https://registry.npmjs.org/feathers-hooks-common/-/feathers-hooks-common-1.5.2.tgz"},"maintainers":[{"name":"daffl","email":"daff@neyeon.de"},{"name":"eddystop","email":"johnsz9999@gmail.com"},{"name":"ekryski","email":"e.kryski@gmail.com"}],"_npmOperationalInternal":{"host":"packages-12-west.internal.npmjs.com","tmp":"tmp/feathers-hooks-common-1.5.2.tgz_1473341338143_0.305583878653124"}},"1.5.3":{"name":"feathers-hooks-common","version":"1.5.3","description":"Useful hooks for use with Feathersjs services.","main":"lib/","directories":{"lib":"lib"},"scripts":{"copy":"rm -rf lib/ && cp -r src/ lib/","babel":"babel src/ --out-dir lib --presets babel-preset-es2015","babel:watch":"babel src/ --watch --out-dir lib --presets babel-preset-es2015","mocha":"mocha test/  --reporter spec --compilers js:babel-core/register","mocha:only":"mocha test/ --reporter spec","eslint":"eslint src/. test/. --ext .js,.jsx","build":"npm run copy && npm run babel","test":"npm run build && npm run eslint && npm run mocha","test:build":"npm run build && npm run mocha:only","test:only":"npm run mocha:only","cover":"node_modules/istanbul/lib/cli.js cover node_modules/mocha/bin/_mocha -- --reporter spec test/*","watch":"npm run copy && npm run babel:watch","npm:patch":"npm version patch && npm publish","npm:minor":"npm version minor && npm publish","npm:major":"npm version major && npm publish","npm:updates":"npm-check-updates"},"repository":{"type":"git","url":"git+https://github.com/feathersjs/feathers-hooks-common.git"},"keywords":["feathers","feathersjs","hook","hooks"],"author":{"name":"John Szwaronek","email":"johnsz9999@gmail.com"},"license":"MIT","bugs":{"url":"https://github.com/feathersjs/feathers-hooks-common/issues"},"homepage":"https://github.com/feathers/feathers-hooks-common#readme","dependencies":{"debug":"^2.2.0","feathers-hooks-utils":"^0.1.1","object.assign":"^4.0.4"},"devDependencies":{"babel-cli":"^6.10.1","babel-core":"^6.10.4","babel-eslint":"6.1.0","babel-plugin-add-module-exports":"^0.2.1","babel-preset-es2015":"^6.9.0","chai":"3.5.0","coveralls":"2.11.9","eslint":"3.0.1","eslint-config-airbnb":"9.0.1","eslint-plugin-import":"1.10.2","eslint-plugin-jsdoc":"2.3.1","eslint-plugin-jsx-a11y":"1.5.5","eslint-plugin-react":"5.2.2","feathers-tests-fake-app-users":"1.0.0","istanbul":"0.4.4","mocha":"2.5.3"},"engines":{"node":">=5.0.0","npm":">=3.8.0"},"gitHead":"d32943ecdae6bbd1e6d5bc1767b1e278e99b724f","_id":"feathers-hooks-common@1.5.3","_shasum":"883169a703a7d4ee1039060b96e9ea845c428fe4","_from":".","_npmVersion":"3.10.5","_nodeVersion":"6.2.2","_npmUser":{"name":"eddystop","email":"johnsz9999@gmail.com"},"dist":{"shasum":"883169a703a7d4ee1039060b96e9ea845c428fe4","tarball":"https://registry.npmjs.org/feathers-hooks-common/-/feathers-hooks-common-1.5.3.tgz"},"maintainers":[{"name":"daffl","email":"daff@neyeon.de"},{"name":"eddystop","email":"johnsz9999@gmail.com"},{"name":"ekryski","email":"e.kryski@gmail.com"}],"_npmOperationalInternal":{"host":"packages-12-west.internal.npmjs.com","tmp":"tmp/feathers-hooks-common-1.5.3.tgz_1473634245701_0.33044186839833856"}},"1.5.4":{"name":"feathers-hooks-common","version":"1.5.4","description":"Useful hooks for use with Feathersjs services.","main":"lib/","directories":{"lib":"lib"},"scripts":{"copy":"rm -rf lib/ && cp -r src/ lib/","babel":"babel src/ --out-dir lib --presets babel-preset-es2015","babel:watch":"babel src/ --watch --out-dir lib --presets babel-preset-es2015","mocha":"mocha test/  --reporter spec --compilers js:babel-core/register","mocha:only":"mocha test/ --reporter spec","eslint":"eslint src/. test/. --ext .js,.jsx","build":"npm run copy && npm run babel","test":"npm run build && npm run eslint && npm run mocha","test:build":"npm run build && npm run mocha:only","test:only":"npm run mocha:only","cover":"node_modules/istanbul/lib/cli.js cover node_modules/mocha/bin/_mocha -- --reporter spec test/*","watch":"npm run copy && npm run babel:watch","npm:patch":"npm version patch && npm publish","npm:minor":"npm version minor && npm publish","npm:major":"npm version major && npm publish","npm:updates":"npm-check-updates"},"repository":{"type":"git","url":"git+https://github.com/feathersjs/feathers-hooks-common.git"},"keywords":["feathers","feathersjs","hook","hooks"],"author":{"name":"John Szwaronek","email":"johnsz9999@gmail.com"},"license":"MIT","bugs":{"url":"https://github.com/feathersjs/feathers-hooks-common/issues"},"homepage":"https://github.com/feathers/feathers-hooks-common#readme","dependencies":{"debug":"^2.2.0","feathers-hooks-utils":"^0.1.1","object.assign":"^4.0.4"},"devDependencies":{"babel-cli":"^6.10.1","babel-core":"^6.10.4","babel-eslint":"6.1.0","babel-plugin-add-module-exports":"^0.2.1","babel-preset-es2015":"^6.9.0","chai":"3.5.0","coveralls":"2.11.9","eslint":"3.0.1","eslint-config-airbnb":"9.0.1","eslint-plugin-import":"1.10.2","eslint-plugin-jsdoc":"2.3.1","eslint-plugin-jsx-a11y":"1.5.5","eslint-plugin-react":"5.2.2","feathers-tests-fake-app-users":"1.0.0","istanbul":"0.4.4","mocha":"2.5.3"},"engines":{"node":">=5.0.0","npm":">=3.8.0"},"gitHead":"7d883f62a7d2e345efa83701a8c8d82b62fc06f6","_id":"feathers-hooks-common@1.5.4","_shasum":"14a27d764a0f73f88d417076222ad193e17552a6","_from":".","_npmVersion":"3.10.5","_nodeVersion":"6.2.2","_npmUser":{"name":"eddystop","email":"johnsz9999@gmail.com"},"dist":{"shasum":"14a27d764a0f73f88d417076222ad193e17552a6","tarball":"https://registry.npmjs.org/feathers-hooks-common/-/feathers-hooks-common-1.5.4.tgz"},"maintainers":[{"name":"daffl","email":"daff@neyeon.de"},{"name":"eddystop","email":"johnsz9999@gmail.com"},{"name":"ekryski","email":"e.kryski@gmail.com"}],"_npmOperationalInternal":{"host":"packages-16-east.internal.npmjs.com","tmp":"tmp/feathers-hooks-common-1.5.4.tgz_1473697128728_0.906704081222415"}},"1.5.5":{"name":"feathers-hooks-common","version":"1.5.5","description":"Useful hooks for use with Feathersjs services.","main":"lib/","directories":{"lib":"lib"},"scripts":{"copy":"rm -rf lib/ && cp -r src/ lib/","babel":"babel src/ --out-dir lib --presets babel-preset-es2015","babel:watch":"babel src/ --watch --out-dir lib --presets babel-preset-es2015","mocha":"mocha test/  --reporter spec --compilers js:babel-core/register","mocha:only":"mocha test/ --reporter spec","eslint":"eslint src/. test/. --ext .js,.jsx","build":"npm run copy && npm run babel","test":"npm run build && npm run eslint && npm run mocha","test:build":"npm run build && npm run mocha:only","test:only":"npm run mocha:only","cover":"node_modules/istanbul/lib/cli.js cover node_modules/mocha/bin/_mocha -- --reporter spec test/*","watch":"npm run copy && npm run babel:watch","npm:patch":"npm version patch && npm publish","npm:minor":"npm version minor && npm publish","npm:major":"npm version major && npm publish","npm:updates":"npm-check-updates"},"repository":{"type":"git","url":"git+https://github.com/feathersjs/feathers-hooks-common.git"},"keywords":["feathers","feathersjs","hook","hooks"],"author":{"name":"John Szwaronek","email":"johnsz9999@gmail.com"},"license":"MIT","bugs":{"url":"https://github.com/feathersjs/feathers-hooks-common/issues"},"homepage":"https://github.com/feathers/feathers-hooks-common#readme","dependencies":{"debug":"^2.2.0","feathers-hooks-utils":"^0.1.1","object.assign":"^4.0.4"},"devDependencies":{"babel-cli":"^6.10.1","babel-core":"^6.10.4","babel-eslint":"6.1.0","babel-plugin-add-module-exports":"^0.2.1","babel-preset-es2015":"^6.9.0","chai":"3.5.0","coveralls":"2.11.9","eslint":"3.0.1","eslint-config-airbnb":"9.0.1","eslint-plugin-import":"1.10.2","eslint-plugin-jsdoc":"2.3.1","eslint-plugin-jsx-a11y":"1.5.5","eslint-plugin-react":"5.2.2","feathers-tests-fake-app-users":"1.0.0","istanbul":"0.4.4","mocha":"2.5.3"},"engines":{"node":">=5.0.0","npm":">=3.8.0"},"gitHead":"90857e882d91e045d45307073b7f63adb5235e33","_id":"feathers-hooks-common@1.5.5","_shasum":"b8908919651b382aeff2ae1c535f260930940fdd","_from":".","_npmVersion":"3.10.5","_nodeVersion":"6.2.2","_npmUser":{"name":"eddystop","email":"johnsz9999@gmail.com"},"dist":{"shasum":"b8908919651b382aeff2ae1c535f260930940fdd","tarball":"https://registry.npmjs.org/feathers-hooks-common/-/feathers-hooks-common-1.5.5.tgz"},"maintainers":[{"name":"daffl","email":"daff@neyeon.de"},{"name":"eddystop","email":"johnsz9999@gmail.com"},{"name":"ekryski","email":"e.kryski@gmail.com"}],"_npmOperationalInternal":{"host":"packages-16-east.internal.npmjs.com","tmp":"tmp/feathers-hooks-common-1.5.5.tgz_1473697544449_0.29480538284406066"}},"1.5.6":{"name":"feathers-hooks-common","version":"1.5.6","description":"Useful hooks for use with Feathersjs services.","main":"lib/","directories":{"lib":"lib"},"scripts":{"copy":"rm -rf lib/ && cp -r src/ lib/","babel":"babel src/ --out-dir lib --presets babel-preset-es2015","babel:watch":"babel src/ --watch --out-dir lib --presets babel-preset-es2015","mocha":"mocha test/  --reporter spec --compilers js:babel-core/register","mocha:only":"mocha test/ --reporter spec","eslint":"eslint src/. test/. --ext .js,.jsx","build":"npm run copy && npm run babel","test":"npm run build && npm run eslint && npm run mocha","test:build":"npm run build && npm run mocha:only","test:only":"npm run mocha:only","cover":"node_modules/istanbul/lib/cli.js cover node_modules/mocha/bin/_mocha -- --reporter spec test/*","watch":"npm run copy && npm run babel:watch","npm:patch":"npm version patch && npm publish","npm:minor":"npm version minor && npm publish","npm:major":"npm version major && npm publish","npm:updates":"npm-check-updates"},"repository":{"type":"git","url":"git+https://github.com/feathersjs/feathers-hooks-common.git"},"keywords":["feathers","feathersjs","hook","hooks"],"author":{"name":"John Szwaronek","email":"johnsz9999@gmail.com"},"license":"MIT","bugs":{"url":"https://github.com/feathersjs/feathers-hooks-common/issues"},"homepage":"https://github.com/feathers/feathers-hooks-common#readme","dependencies":{"debug":"^2.2.0","feathers-hooks-utils":"^0.1.1","object.assign":"^4.0.4"},"devDependencies":{"babel-cli":"^6.10.1","babel-core":"^6.10.4","babel-eslint":"6.1.0","babel-plugin-add-module-exports":"^0.2.1","babel-preset-es2015":"^6.9.0","chai":"3.5.0","coveralls":"2.11.9","eslint":"3.0.1","eslint-config-airbnb":"9.0.1","eslint-plugin-import":"1.10.2","eslint-plugin-jsdoc":"2.3.1","eslint-plugin-jsx-a11y":"1.5.5","eslint-plugin-react":"5.2.2","feathers-tests-fake-app-users":"1.0.0","istanbul":"0.4.4","mocha":"2.5.3"},"engines":{"node":">=5.0.0","npm":">=3.8.0"},"gitHead":"7b898183619181f7659d03eaadb44478ccd2a067","_id":"feathers-hooks-common@1.5.6","_shasum":"f4c7867a14878073f71373d6109ad57bc63ad087","_from":".","_npmVersion":"3.10.5","_nodeVersion":"6.2.2","_npmUser":{"name":"eddystop","email":"johnsz9999@gmail.com"},"dist":{"shasum":"f4c7867a14878073f71373d6109ad57bc63ad087","tarball":"https://registry.npmjs.org/feathers-hooks-common/-/feathers-hooks-common-1.5.6.tgz"},"maintainers":[{"name":"daffl","email":"daff@neyeon.de"},{"name":"eddystop","email":"johnsz9999@gmail.com"},{"name":"ekryski","email":"e.kryski@gmail.com"}],"_npmOperationalInternal":{"host":"packages-16-east.internal.npmjs.com","tmp":"tmp/feathers-hooks-common-1.5.6.tgz_1473699518524_0.09058098657988012"}},"1.5.7":{"name":"feathers-hooks-common","version":"1.5.7","description":"Useful hooks for use with Feathersjs services.","main":"lib/","directories":{"lib":"lib"},"scripts":{"copy":"rm -rf lib/ && cp -r src/ lib/","babel":"babel src/ --out-dir lib --presets babel-preset-es2015","babel:watch":"babel src/ --watch --out-dir lib --presets babel-preset-es2015","mocha":"mocha test/  --reporter spec --compilers js:babel-core/register","mocha:only":"mocha test/ --reporter spec","eslint":"eslint src/. test/. --ext .js,.jsx","build":"npm run copy && npm run babel","test":"npm run build && npm run eslint && npm run mocha","test:build":"npm run build && npm run mocha:only","test:only":"npm run mocha:only","cover":"node_modules/istanbul/lib/cli.js cover node_modules/mocha/bin/_mocha -- --reporter spec test/*","watch":"npm run copy && npm run babel:watch","npm:patch":"npm version patch && npm publish","npm:minor":"npm version minor && npm publish","npm:major":"npm version major && npm publish","npm:updates":"npm-check-updates"},"repository":{"type":"git","url":"git+https://github.com/feathersjs/feathers-hooks-common.git"},"keywords":["feathers","feathersjs","hook","hooks"],"author":{"name":"John Szwaronek","email":"johnsz9999@gmail.com"},"license":"MIT","bugs":{"url":"https://github.com/feathersjs/feathers-hooks-common/issues"},"homepage":"https://github.com/feathers/feathers-hooks-common#readme","dependencies":{"debug":"^2.2.0","feathers-hooks-utils":"^0.1.1","object.assign":"^4.0.4"},"devDependencies":{"babel-cli":"^6.10.1","babel-core":"^6.10.4","babel-eslint":"6.1.0","babel-plugin-add-module-exports":"^0.2.1","babel-preset-es2015":"^6.9.0","chai":"3.5.0","coveralls":"2.11.9","eslint":"3.0.1","eslint-config-airbnb":"9.0.1","eslint-plugin-import":"1.10.2","eslint-plugin-jsdoc":"2.3.1","eslint-plugin-jsx-a11y":"1.5.5","eslint-plugin-react":"5.2.2","feathers-tests-fake-app-users":"1.0.0","istanbul":"0.4.4","mocha":"2.5.3"},"engines":{"node":">=5.0.0","npm":">=3.8.0"},"gitHead":"16e7b1ccde177c91a30db8df33a033dd58f869fc","_id":"feathers-hooks-common@1.5.7","_shasum":"6370fd63aeb1cac25329bec262fd5ce842c99601","_from":".","_npmVersion":"3.10.5","_nodeVersion":"6.2.2","_npmUser":{"name":"eddystop","email":"johnsz9999@gmail.com"},"dist":{"shasum":"6370fd63aeb1cac25329bec262fd5ce842c99601","tarball":"https://registry.npmjs.org/feathers-hooks-common/-/feathers-hooks-common-1.5.7.tgz"},"maintainers":[{"name":"daffl","email":"daff@neyeon.de"},{"name":"eddystop","email":"johnsz9999@gmail.com"},{"name":"ekryski","email":"e.kryski@gmail.com"}],"_npmOperationalInternal":{"host":"packages-12-west.internal.npmjs.com","tmp":"tmp/feathers-hooks-common-1.5.7.tgz_1473780814622_0.32067832024767995"}},"1.5.8":{"name":"feathers-hooks-common","version":"1.5.8","description":"Useful hooks for use with Feathersjs services.","main":"lib/","directories":{"lib":"lib"},"scripts":{"copy":"rm -rf lib/ && cp -r src/ lib/","babel":"babel src/ --out-dir lib --presets babel-preset-es2015","babel:watch":"babel src/ --watch --out-dir lib --presets babel-preset-es2015","mocha":"mocha test/  --reporter spec --compilers js:babel-core/register","mocha:only":"mocha test/ --reporter spec","eslint":"eslint src/. test/. --ext .js,.jsx","build":"npm run copy && npm run babel","test":"npm run build && npm run eslint && npm run mocha","test:build":"npm run build && npm run mocha:only","test:only":"npm run mocha:only","cover":"node_modules/istanbul/lib/cli.js cover node_modules/mocha/bin/_mocha -- --reporter spec test/*","watch":"npm run copy && npm run babel:watch","npm:patch":"npm version patch && npm publish","npm:minor":"npm version minor && npm publish","npm:major":"npm version major && npm publish","npm:updates":"npm-check-updates"},"repository":{"type":"git","url":"git+https://github.com/feathersjs/feathers-hooks-common.git"},"keywords":["feathers","feathersjs","hook","hooks"],"author":{"name":"John Szwaronek","email":"johnsz9999@gmail.com"},"license":"MIT","bugs":{"url":"https://github.com/feathersjs/feathers-hooks-common/issues"},"homepage":"https://github.com/feathers/feathers-hooks-common#readme","dependencies":{"debug":"^2.2.0","feathers-hooks-utils":"^0.1.1","object.assign":"^4.0.4"},"devDependencies":{"babel-cli":"^6.10.1","babel-core":"^6.10.4","babel-eslint":"6.1.0","babel-plugin-add-module-exports":"^0.2.1","babel-preset-es2015":"^6.9.0","chai":"3.5.0","coveralls":"2.11.9","eslint":"3.0.1","eslint-config-airbnb":"9.0.1","eslint-plugin-import":"1.10.2","eslint-plugin-jsdoc":"2.3.1","eslint-plugin-jsx-a11y":"1.5.5","eslint-plugin-react":"5.2.2","feathers-tests-fake-app-users":"1.0.0","istanbul":"0.4.4","mocha":"2.5.3"},"engines":{"node":">=5.0.0","npm":">=3.8.0"},"gitHead":"372f7b6a7ad8bd3f4844ca8b672742730d35832b","_id":"feathers-hooks-common@1.5.8","_shasum":"fe20dba024cae82f1427ebc7dbe0e23ce82633fa","_from":".","_npmVersion":"3.10.7","_nodeVersion":"6.2.2","_npmUser":{"name":"eddystop","email":"johnsz9999@gmail.com"},"dist":{"shasum":"fe20dba024cae82f1427ebc7dbe0e23ce82633fa","tarball":"https://registry.npmjs.org/feathers-hooks-common/-/feathers-hooks-common-1.5.8.tgz"},"maintainers":[{"name":"daffl","email":"daff@neyeon.de"},{"name":"eddystop","email":"johnsz9999@gmail.com"},{"name":"ekryski","email":"e.kryski@gmail.com"}],"_npmOperationalInternal":{"host":"packages-12-west.internal.npmjs.com","tmp":"tmp/feathers-hooks-common-1.5.8.tgz_1473862307844_0.04748721816577017"}},"1.6.0":{"name":"feathers-hooks-common","version":"1.6.0","description":"Useful hooks for use with Feathersjs services.","main":"lib/","directories":{"lib":"lib"},"scripts":{"copy":"rm -rf lib/ && cp -r src/ lib/","babel":"babel src/ --out-dir lib --presets babel-preset-es2015","babel:watch":"babel src/ --watch --out-dir lib --presets babel-preset-es2015","mocha":"mocha test/  --reporter spec --compilers js:babel-core/register","mocha:only":"mocha test/ --reporter spec","eslint":"eslint src/. test/. --ext .js,.jsx","build":"npm run copy && npm run babel","test":"npm run build && npm run eslint && npm run mocha","test:build":"npm run build && npm run mocha:only","test:only":"npm run mocha:only","cover":"node_modules/istanbul/lib/cli.js cover node_modules/mocha/bin/_mocha -- --reporter spec test/*","watch":"npm run copy && npm run babel:watch","npm:patch":"npm version patch && npm publish","npm:minor":"npm version minor && npm publish","npm:major":"npm version major && npm publish","npm:updates":"npm-check-updates"},"repository":{"type":"git","url":"git+https://github.com/feathersjs/feathers-hooks-common.git"},"keywords":["feathers","feathersjs","hook","hooks"],"author":{"name":"John Szwaronek","email":"johnsz9999@gmail.com"},"license":"MIT","bugs":{"url":"https://github.com/feathersjs/feathers-hooks-common/issues"},"homepage":"https://github.com/feathers/feathers-hooks-common#readme","dependencies":{"debug":"^2.2.0","feathers-hooks-utils":"^0.1.1","get-parameter-names":"git+https://github.com/benbotto/get-parameter-names.git","object.assign":"^4.0.4"},"devDependencies":{"babel-cli":"^6.10.1","babel-core":"^6.10.4","babel-eslint":"6.1.0","babel-plugin-add-module-exports":"^0.2.1","babel-preset-es2015":"^6.9.0","chai":"3.5.0","coveralls":"2.11.9","eslint":"3.0.1","eslint-config-airbnb":"9.0.1","eslint-plugin-import":"1.10.2","eslint-plugin-jsdoc":"2.3.1","eslint-plugin-jsx-a11y":"1.5.5","eslint-plugin-react":"5.2.2","feathers-tests-fake-app-users":"1.0.0","istanbul":"0.4.4","mocha":"2.5.3"},"engines":{"node":">=5.0.0","npm":">=3.8.0"},"gitHead":"8f944d6e69f330a4cbac6629687a3f1fa221914b","_id":"feathers-hooks-common@1.6.0","_shasum":"e54107160b9fc76be1d911a58f2783b39c12b997","_from":".","_npmVersion":"3.10.7","_nodeVersion":"6.2.2","_npmUser":{"name":"eddystop","email":"johnsz9999@gmail.com"},"dist":{"shasum":"e54107160b9fc76be1d911a58f2783b39c12b997","tarball":"https://registry.npmjs.org/feathers-hooks-common/-/feathers-hooks-common-1.6.0.tgz"},"maintainers":[{"name":"daffl","email":"daff@neyeon.de"},{"name":"eddystop","email":"johnsz9999@gmail.com"},{"name":"ekryski","email":"e.kryski@gmail.com"}],"_npmOperationalInternal":{"host":"packages-12-west.internal.npmjs.com","tmp":"tmp/feathers-hooks-common-1.6.0.tgz_1475436043598_0.36419862671755254"}},"1.6.1":{"name":"feathers-hooks-common","version":"1.6.1","description":"Useful hooks for use with Feathersjs services.","main":"lib/","directories":{"lib":"lib"},"scripts":{"copy":"rm -rf lib/ && cp -r src/ lib/","babel":"babel src/ --out-dir lib --presets babel-preset-es2015","babel:watch":"babel src/ --watch --out-dir lib --presets babel-preset-es2015","mocha":"mocha test/  --reporter spec --compilers js:babel-core/register","mocha:only":"mocha test/ --reporter spec","eslint":"eslint src/. test/. --ext .js,.jsx","build":"npm run copy && npm run babel","test":"npm run build && npm run eslint && npm run mocha","test:build":"npm run build && npm run mocha:only","test:only":"npm run mocha:only","cover":"node_modules/istanbul/lib/cli.js cover node_modules/mocha/bin/_mocha -- --reporter spec test/*","watch":"npm run copy && npm run babel:watch","npm:patch":"npm version patch && npm publish","npm:minor":"npm version minor && npm publish","npm:major":"npm version major && npm publish","npm:updates":"npm-check-updates"},"repository":{"type":"git","url":"git+https://github.com/feathersjs/feathers-hooks-common.git"},"keywords":["feathers","feathersjs","hook","hooks"],"author":{"name":"John Szwaronek","email":"johnsz9999@gmail.com"},"license":"MIT","bugs":{"url":"https://github.com/feathersjs/feathers-hooks-common/issues"},"homepage":"https://github.com/feathers/feathers-hooks-common#readme","dependencies":{"debug":"^2.2.0","feathers-hooks-utils":"^0.1.1","get-parameter-names":"git+https://github.com/benbotto/get-parameter-names.git","object.assign":"^4.0.4"},"devDependencies":{"babel-cli":"^6.10.1","babel-core":"^6.10.4","babel-eslint":"6.1.0","babel-plugin-add-module-exports":"^0.2.1","babel-preset-es2015":"^6.9.0","chai":"3.5.0","coveralls":"2.11.9","eslint":"3.0.1","eslint-config-airbnb":"9.0.1","eslint-plugin-import":"1.10.2","eslint-plugin-jsdoc":"2.3.1","eslint-plugin-jsx-a11y":"1.5.5","eslint-plugin-react":"5.2.2","feathers-tests-fake-app-users":"1.0.0","istanbul":"0.4.4","mocha":"2.5.3"},"engines":{"node":">=5.0.0","npm":">=3.8.0"},"gitHead":"b88ffe34113185a06895e4818ff20de2a671e785","_id":"feathers-hooks-common@1.6.1","_shasum":"48f7c58e548a7bb91e15e6c4d09d439f1da514e4","_from":".","_npmVersion":"3.10.7","_nodeVersion":"6.2.2","_npmUser":{"name":"eddystop","email":"johnsz9999@gmail.com"},"dist":{"shasum":"48f7c58e548a7bb91e15e6c4d09d439f1da514e4","tarball":"https://registry.npmjs.org/feathers-hooks-common/-/feathers-hooks-common-1.6.1.tgz"},"maintainers":[{"name":"daffl","email":"daff@neyeon.de"},{"name":"eddystop","email":"johnsz9999@gmail.com"},{"name":"ekryski","email":"e.kryski@gmail.com"}],"_npmOperationalInternal":{"host":"packages-16-east.internal.npmjs.com","tmp":"tmp/feathers-hooks-common-1.6.1.tgz_1475436795135_0.4434056815225631"}},"1.6.2":{"name":"feathers-hooks-common","version":"1.6.2","description":"Useful hooks for use with Feathersjs services.","main":"lib/","directories":{"lib":"lib"},"scripts":{"copy":"rm -rf lib/ && cp -r src/ lib/","babel":"babel src/ --out-dir lib --presets babel-preset-es2015","babel:watch":"babel src/ --watch --out-dir lib --presets babel-preset-es2015","mocha":"mocha test/  --reporter spec --compilers js:babel-core/register","mocha:only":"mocha test/ --reporter spec","eslint":"eslint src/. test/. --ext .js,.jsx","build":"npm run copy && npm run babel","test":"npm run build && npm run eslint && npm run mocha","test:build":"npm run build && npm run mocha:only","test:only":"npm run mocha:only","cover":"node_modules/istanbul/lib/cli.js cover node_modules/mocha/bin/_mocha -- --reporter spec test/*","watch":"npm run copy && npm run babel:watch","npm:patch":"npm version patch && npm publish","npm:minor":"npm version minor && npm publish","npm:major":"npm version major && npm publish","npm:updates":"npm-check-updates"},"repository":{"type":"git","url":"git+https://github.com/feathersjs/feathers-hooks-common.git"},"keywords":["feathers","feathersjs","hook","hooks"],"author":{"name":"John Szwaronek","email":"johnsz9999@gmail.com"},"license":"MIT","bugs":{"url":"https://github.com/feathersjs/feathers-hooks-common/issues"},"homepage":"https://github.com/feathers/feathers-hooks-common#readme","dependencies":{"debug":"^2.2.0","feathers-hooks-utils":"^0.1.1","get-parameter-names":"git+https://github.com/benbotto/get-parameter-names.git","object.assign":"^4.0.4"},"devDependencies":{"babel-cli":"^6.10.1","babel-core":"^6.10.4","babel-eslint":"6.1.0","babel-plugin-add-module-exports":"^0.2.1","babel-preset-es2015":"^6.9.0","chai":"3.5.0","coveralls":"2.11.9","eslint":"3.0.1","eslint-config-airbnb":"9.0.1","eslint-plugin-import":"1.10.2","eslint-plugin-jsdoc":"2.3.1","eslint-plugin-jsx-a11y":"1.5.5","eslint-plugin-react":"5.2.2","feathers-tests-fake-app-users":"1.0.0","istanbul":"0.4.4","mocha":"2.5.3"},"engines":{"node":">=5.0.0","npm":">=3.8.0"},"gitHead":"1d738b06cc0f549d5fd79f0998dfb3c5e3345a0d","_id":"feathers-hooks-common@1.6.2","_shasum":"ecb71aec946cc2d1d6ff8f6ac89019b59193b142","_from":".","_npmVersion":"3.10.7","_nodeVersion":"6.2.2","_npmUser":{"name":"eddystop","email":"johnsz9999@gmail.com"},"dist":{"shasum":"ecb71aec946cc2d1d6ff8f6ac89019b59193b142","tarball":"https://registry.npmjs.org/feathers-hooks-common/-/feathers-hooks-common-1.6.2.tgz"},"maintainers":[{"name":"daffl","email":"daff@neyeon.de"},{"name":"eddystop","email":"johnsz9999@gmail.com"},{"name":"ekryski","email":"e.kryski@gmail.com"}],"_npmOperationalInternal":{"host":"packages-16-east.internal.npmjs.com","tmp":"tmp/feathers-hooks-common-1.6.2.tgz_1475455016062_0.7802956223022193"}},"1.7.0":{"name":"feathers-hooks-common","version":"1.7.0","description":"Useful hooks for use with Feathersjs services.","main":"lib/","directories":{"lib":"lib"},"scripts":{"copy":"rm -rf lib/ && cp -r src/ lib/","babel":"babel src/ --out-dir lib --presets babel-preset-es2015","babel:watch":"babel src/ --watch --out-dir lib --presets babel-preset-es2015","mocha":"mocha test/  --reporter spec --compilers js:babel-core/register","mocha:only":"mocha test/ --reporter spec","eslint":"eslint src/. test/. --ext .js,.jsx","build":"npm run copy && npm run babel","test":"npm run build && npm run eslint && npm run mocha","test:build":"npm run build && npm run mocha:only","test:only":"npm run mocha:only","cover":"node_modules/istanbul/lib/cli.js cover node_modules/mocha/bin/_mocha -- --reporter spec test/*","watch":"npm run copy && npm run babel:watch","npm:patch":"npm version patch && npm publish","npm:minor":"npm version minor && npm publish","npm:major":"npm version major && npm publish","npm:updates":"npm-check-updates","changelog":"git log --pretty=format:'%h% B'"},"repository":{"type":"git","url":"git+https://github.com/feathersjs/feathers-hooks-common.git"},"keywords":["feathers","feathersjs","hook","hooks"],"author":{"name":"John Szwaronek","email":"johnsz9999@gmail.com"},"license":"MIT","bugs":{"url":"https://github.com/feathersjs/feathers-hooks-common/issues"},"homepage":"https://github.com/feathers/feathers-hooks-common#readme","dependencies":{"debug":"^2.2.0","feathers-hooks-utils":"^0.1.1","get-parameter-names":"git+https://github.com/benbotto/get-parameter-names.git","object.assign":"^4.0.4"},"devDependencies":{"babel-cli":"^6.10.1","babel-core":"^6.10.4","babel-eslint":"6.1.0","babel-plugin-add-module-exports":"^0.2.1","babel-preset-es2015":"^6.9.0","chai":"3.5.0","coveralls":"2.11.9","eslint":"3.0.1","eslint-config-airbnb":"9.0.1","eslint-plugin-import":"1.10.2","eslint-plugin-jsdoc":"2.3.1","eslint-plugin-jsx-a11y":"1.5.5","eslint-plugin-react":"5.2.2","feathers-tests-fake-app-users":"1.0.0","istanbul":"0.4.4","mocha":"2.5.3"},"engines":{"node":">=5.0.0","npm":">=3.8.0"},"gitHead":"7de43d0475ab45d880ade8498db78f256b89bac7","_id":"feathers-hooks-common@1.7.0","_shasum":"602f7eea868bdee9ca4de67194a905dea2b9ce22","_from":".","_npmVersion":"3.10.7","_nodeVersion":"6.2.2","_npmUser":{"name":"eddystop","email":"johnsz9999@gmail.com"},"dist":{"shasum":"602f7eea868bdee9ca4de67194a905dea2b9ce22","tarball":"https://registry.npmjs.org/feathers-hooks-common/-/feathers-hooks-common-1.7.0.tgz"},"maintainers":[{"name":"daffl","email":"daff@neyeon.de"},{"name":"eddystop","email":"johnsz9999@gmail.com"},{"name":"ekryski","email":"e.kryski@gmail.com"}],"_npmOperationalInternal":{"host":"packages-12-west.internal.npmjs.com","tmp":"tmp/feathers-hooks-common-1.7.0.tgz_1475587582405_0.3101831595413387"}},"1.7.1":{"name":"feathers-hooks-common","version":"1.7.1","description":"Useful hooks for use with Feathersjs services.","main":"lib/","directories":{"lib":"lib"},"scripts":{"copy":"rm -rf lib/ && cp -r src/ lib/","babel":"babel src/ --out-dir lib --presets babel-preset-es2015","babel:watch":"babel src/ --watch --out-dir lib --presets babel-preset-es2015","mocha":"mocha test/  --reporter spec --compilers js:babel-core/register","mocha:only":"mocha test/ --reporter spec","eslint":"eslint src/. test/. --ext .js,.jsx","build":"npm run copy && npm run babel","test":"npm run build && npm run eslint && npm run mocha","test:build":"npm run build && npm run mocha:only","test:only":"npm run mocha:only","cover":"node_modules/istanbul/lib/cli.js cover node_modules/mocha/bin/_mocha -- --reporter spec test/*","watch":"npm run copy && npm run babel:watch","npm:patch":"npm version patch && npm publish","npm:minor":"npm version minor && npm publish","npm:major":"npm version major && npm publish","npm:updates":"npm-check-updates","changelog":"git log --pretty=format:'%h% B'"},"repository":{"type":"git","url":"git+https://github.com/feathersjs/feathers-hooks-common.git"},"keywords":["feathers","feathersjs","hook","hooks"],"author":{"name":"John Szwaronek","email":"johnsz9999@gmail.com"},"license":"MIT","bugs":{"url":"https://github.com/feathersjs/feathers-hooks-common/issues"},"homepage":"https://github.com/feathers/feathers-hooks-common#readme","dependencies":{"debug":"^2.2.0","feathers-hooks-utils":"^0.1.1","get-parameter-names":"git+https://github.com/benbotto/get-parameter-names.git","object.assign":"^4.0.4"},"devDependencies":{"babel-cli":"^6.10.1","babel-core":"^6.10.4","babel-eslint":"6.1.0","babel-plugin-add-module-exports":"^0.2.1","babel-preset-es2015":"^6.9.0","chai":"3.5.0","coveralls":"2.11.9","eslint":"3.0.1","eslint-config-airbnb":"9.0.1","eslint-plugin-import":"1.10.2","eslint-plugin-jsdoc":"2.3.1","eslint-plugin-jsx-a11y":"1.5.5","eslint-plugin-react":"5.2.2","feathers-tests-fake-app-users":"1.0.0","istanbul":"0.4.4","mocha":"2.5.3"},"engines":{"node":">=5.0.0","npm":">=3.8.0"},"gitHead":"a630aa7a640c77d81b7e0893dc866b6434fb78b4","_id":"feathers-hooks-common@1.7.1","_shasum":"69d64db893c2afb1f9c76a2307f701a9766c2e8a","_from":".","_npmVersion":"3.10.7","_nodeVersion":"6.2.2","_npmUser":{"name":"eddystop","email":"johnsz9999@gmail.com"},"dist":{"shasum":"69d64db893c2afb1f9c76a2307f701a9766c2e8a","tarball":"https://registry.npmjs.org/feathers-hooks-common/-/feathers-hooks-common-1.7.1.tgz"},"maintainers":[{"name":"daffl","email":"daff@neyeon.de"},{"name":"eddystop","email":"johnsz9999@gmail.com"},{"name":"ekryski","email":"e.kryski@gmail.com"}],"_npmOperationalInternal":{"host":"packages-16-east.internal.npmjs.com","tmp":"tmp/feathers-hooks-common-1.7.1.tgz_1475765105949_0.1550147079396993"}},"1.7.2":{"name":"feathers-hooks-common","version":"1.7.2","description":"Useful hooks for use with Feathersjs services.","main":"lib/","directories":{"lib":"lib"},"scripts":{"copy":"rm -rf lib/ && cp -r src/ lib/","babel":"babel src/ --out-dir lib --presets babel-preset-es2015","babel:watch":"babel src/ --watch --out-dir lib --presets babel-preset-es2015","mocha":"mocha test/  --reporter spec --compilers js:babel-core/register","mocha:only":"mocha test/ --reporter spec","eslint":"eslint src/. test/. --ext .js,.jsx","build":"npm run copy && npm run babel","test":"npm run build && npm run eslint && npm run mocha","test:build":"npm run build && npm run mocha:only","test:only":"npm run mocha:only","cover":"node_modules/istanbul/lib/cli.js cover node_modules/mocha/bin/_mocha -- --reporter spec test/*","watch":"npm run copy && npm run babel:watch","npm:patch":"npm version patch && npm publish","npm:minor":"npm version minor && npm publish","npm:major":"npm version major && npm publish","npm:updates":"npm-check-updates","changelog":"git log --pretty=format:'%h% B'"},"repository":{"type":"git","url":"git+https://github.com/feathersjs/feathers-hooks-common.git"},"keywords":["feathers","feathersjs","hook","hooks"],"author":{"name":"John Szwaronek","email":"johnsz9999@gmail.com"},"license":"MIT","bugs":{"url":"https://github.com/feathersjs/feathers-hooks-common/issues"},"homepage":"https://github.com/feathers/feathers-hooks-common#readme","dependencies":{"debug":"^2.2.0","feathers-hooks-utils":"^0.1.1","get-parameter-names":"git+https://github.com/benbotto/get-parameter-names.git","object.assign":"^4.0.4"},"devDependencies":{"babel-cli":"^6.10.1","babel-core":"^6.10.4","babel-eslint":"6.1.0","babel-plugin-add-module-exports":"^0.2.1","babel-preset-es2015":"^6.9.0","chai":"3.5.0","coveralls":"2.11.9","eslint":"3.0.1","eslint-config-airbnb":"9.0.1","eslint-plugin-import":"1.10.2","eslint-plugin-jsdoc":"2.3.1","eslint-plugin-jsx-a11y":"1.5.5","eslint-plugin-react":"5.2.2","feathers-tests-fake-app-users":"1.0.0","istanbul":"0.4.4","mocha":"2.5.3"},"engines":{"node":">=5.0.0","npm":">=3.8.0"},"gitHead":"c20cbd5be6e3840adaa270a85433fc5d1f76749e","_id":"feathers-hooks-common@1.7.2","_shasum":"d779423eefa76d2506eb63523c2e8230f6c15723","_from":".","_npmVersion":"3.10.7","_nodeVersion":"6.2.2","_npmUser":{"name":"eddystop","email":"johnsz9999@gmail.com"},"dist":{"shasum":"d779423eefa76d2506eb63523c2e8230f6c15723","tarball":"https://registry.npmjs.org/feathers-hooks-common/-/feathers-hooks-common-1.7.2.tgz"},"maintainers":[{"name":"daffl","email":"daff@neyeon.de"},{"name":"eddystop","email":"johnsz9999@gmail.com"},{"name":"ekryski","email":"e.kryski@gmail.com"}],"_npmOperationalInternal":{"host":"packages-12-west.internal.npmjs.com","tmp":"tmp/feathers-hooks-common-1.7.2.tgz_1475850063151_0.6435845529194921"}},"2.0.0":{"name":"feathers-hooks-common","version":"2.0.0","description":"Useful hooks for use with Feathersjs services.","main":"lib/","directories":{"lib":"lib"},"scripts":{"copy":"rimraf lib/ && cp -r src/ lib/","babel":"babel src/ --out-dir lib --presets babel-preset-es2015","babel:watch":"babel src/ --watch --out-dir lib --presets babel-preset-es2015","mocha":"mocha test/  --reporter spec --opts mocha.opts","mocha:only":"mocha test/ --reporter spec --opts mocha.opts","lint":"eslint-if-supported semistandard","lint:fix":"eslint-if-supported semistandard --fix","build":"npm run copy && npm run babel","test":"npm run build && npm run lint && npm run mocha","test:build":"npm run build && npm run mocha:only","test:only":"npm run mocha:only","cover":"node_modules/istanbul/lib/cli.js cover node_modules/mocha/bin/_mocha -- --reporter spec test/*","watch":"npm run copy && npm run babel:watch","npm:patch":"npm version patch && npm publish","npm:minor":"npm version minor && npm publish","npm:major":"npm version major && npm publish","npm:updates":"npm-check-updates","changelog":"git log --pretty=format:'%h% B'"},"semistandard":{"env":["mocha"],"ignore":["/lib"]},"repository":{"type":"git","url":"git+https://github.com/feathersjs/feathers-hooks-common.git"},"keywords":["feathers","feathersjs","hook","hooks"],"author":{"name":"John Szwaronek","email":"johnsz9999@gmail.com"},"license":"MIT","bugs":{"url":"https://github.com/feathersjs/feathers-hooks-common/issues"},"homepage":"https://github.com/feathers/feathers-hooks-common#readme","dependencies":{"debug":"^2.2.0","feathers-errors":"^2.4.0"},"devDependencies":{"babel-cli":"^6.16.0","babel-core":"^6.17.0","babel-plugin-add-module-exports":"^0.2.1","babel-polyfill":"6.16.0","babel-preset-es2015":"^6.16.0","chai":"^3.5.0","coveralls":"^2.11.14","eslint-if-supported":"^1.0.1","feathers-tests-fake-app-users":"^1.0.0","istanbul":"^0.4.5","mocha":"^2.5.3","rimraf":"^2.5.4","semistandard":"^9.1.0"},"engines":{"node":">=4.6.1","npm":">=2.15.9"},"gitHead":"7d456a6aa46357a60c1a7f8481ebc8c4edffacb0","_id":"feathers-hooks-common@2.0.0","_shasum":"bc851b8fa7e233ca0521f083e8a89b4114ea9470","_from":".","_npmVersion":"3.10.3","_nodeVersion":"6.7.0","_npmUser":{"name":"daffl","email":"daff@neyeon.de"},"dist":{"shasum":"bc851b8fa7e233ca0521f083e8a89b4114ea9470","tarball":"https://registry.npmjs.org/feathers-hooks-common/-/feathers-hooks-common-2.0.0.tgz"},"maintainers":[{"name":"daffl","email":"daff@neyeon.de"},{"name":"eddystop","email":"johnsz9999@gmail.com"},{"name":"ekryski","email":"e.kryski@gmail.com"}],"_npmOperationalInternal":{"host":"packages-18-east.internal.npmjs.com","tmp":"tmp/feathers-hooks-common-2.0.0.tgz_1477768250805_0.11219385778531432"}},"2.0.1":{"name":"feathers-hooks-common","version":"2.0.1","description":"Useful hooks for use with Feathersjs services.","main":"lib/","directories":{"lib":"lib"},"scripts":{"prepublish":"npm run compile","publish":"git push origin --tags && npm run changelog && git push origin","release:prerelease":"npm version prerelease && npm publish","release:patch":"npm version patch && npm publish","release:minor":"npm version minor && npm publish","release:major":"npm version major && npm publish","changelog":"github_changelog_generator && git add CHANGELOG.md && git commit -am \"Updating changelog\"","compile":"rimraf lib/ && babel -d lib/ src/","watch":"babel --watch -d lib/ src/","lint":"eslint-if-supported semistandard --fix","mocha":"mocha --opts mocha.opts","coverage":"istanbul cover node_modules/mocha/bin/_mocha -- --opts mocha.opts","test":"npm run compile && npm run lint && npm run coverage"},"semistandard":{"env":["mocha"],"ignore":["/lib"]},"repository":{"type":"git","url":"git+https://github.com/feathersjs/feathers-hooks-common.git"},"keywords":["feathers","feathersjs","hook","hooks"],"author":{"name":"John Szwaronek","email":"johnsz9999@gmail.com"},"license":"MIT","bugs":{"url":"https://github.com/feathersjs/feathers-hooks-common/issues"},"homepage":"https://github.com/feathers/feathers-hooks-common#readme","dependencies":{"debug":"^2.2.0","feathers-errors":"^2.4.0"},"devDependencies":{"babel-cli":"^6.16.0","babel-core":"^6.17.0","babel-plugin-add-module-exports":"^0.2.1","babel-polyfill":"6.16.0","babel-preset-es2015":"^6.16.0","chai":"^3.5.0","coveralls":"^2.11.14","eslint-if-supported":"^1.0.1","feathers-tests-fake-app-users":"^1.0.0","istanbul":"^1.1.0-alpha.1","rimraf":"^2.5.4","semistandard":"^9.1.0","mocha":"^3.1.2"},"engines":{"node":">= 4.6.1","npm":">= 2.15.9"},"gitHead":"9220628050d121e792c317ae1d072cda0934aee8","_id":"feathers-hooks-common@2.0.1","_shasum":"f7923d08791369400de774eb7639a387f6b90312","_from":".","_npmVersion":"3.10.6","_nodeVersion":"6.4.0","_npmUser":{"name":"ekryski","email":"e.kryski@gmail.com"},"dist":{"shasum":"f7923d08791369400de774eb7639a387f6b90312","tarball":"https://registry.npmjs.org/feathers-hooks-common/-/feathers-hooks-common-2.0.1.tgz"},"maintainers":[{"name":"daffl","email":"daff@neyeon.de"},{"name":"eddystop","email":"johnsz9999@gmail.com"},{"name":"ekryski","email":"e.kryski@gmail.com"}],"_npmOperationalInternal":{"host":"packages-12-west.internal.npmjs.com","tmp":"tmp/feathers-hooks-common-2.0.1.tgz_1478296030965_0.960869061993435"}},"2.0.2":{"name":"feathers-hooks-common","version":"2.0.2","description":"Useful hooks for use with Feathersjs services.","main":"lib/","directories":{"lib":"lib"},"scripts":{"prepublish":"npm run compile","publish":"git push origin --tags && npm run changelog && git push origin","release:prerelease":"npm version prerelease && npm publish","release:patch":"npm version patch && npm publish","release:minor":"npm version minor && npm publish","release:major":"npm version major && npm publish","changelog":"github_changelog_generator && git add CHANGELOG.md && git commit -am \"Updating changelog\"","compile":"rimraf lib/ && babel -d lib/ src/","watch":"babel --watch -d lib/ src/","lint":"eslint-if-supported semistandard --fix","mocha":"mocha --opts mocha.opts","coverage":"istanbul cover node_modules/mocha/bin/_mocha -- --opts mocha.opts","test":"npm run compile && npm run lint && npm run coverage"},"semistandard":{"env":["mocha"],"ignore":["/lib"]},"repository":{"type":"git","url":"git+https://github.com/feathersjs/feathers-hooks-common.git"},"keywords":["feathers","feathersjs","hook","hooks"],"author":{"name":"John Szwaronek","email":"johnsz9999@gmail.com"},"license":"MIT","bugs":{"url":"https://github.com/feathersjs/feathers-hooks-common/issues"},"homepage":"https://github.com/feathers/feathers-hooks-common#readme","dependencies":{"debug":"^2.2.0","feathers-errors":"^2.4.0"},"devDependencies":{"babel-cli":"^6.16.0","babel-core":"^6.17.0","babel-plugin-add-module-exports":"^0.2.1","babel-polyfill":"6.16.0","babel-preset-es2015":"^6.16.0","chai":"^3.5.0","coveralls":"^2.11.14","eslint-if-supported":"^1.0.1","feathers":"2.0.2","feathers-hooks":"1.7.0","feathers-memory":"1.0.1","feathers-tests-fake-app-users":"^1.0.0","istanbul":"^1.1.0-alpha.1","mocha":"^3.1.2","rimraf":"^2.5.4","semistandard":"^9.1.0"},"engines":{"node":">= 4.6.1"},"gitHead":"60907c4633178b7437b3c23489bc60ae9a1dc3fe","_id":"feathers-hooks-common@2.0.2","_shasum":"457e5337280eae85a40bc79034371aa43fd8bb19","_from":".","_npmVersion":"3.10.8","_nodeVersion":"6.9.0","_npmUser":{"name":"eddystop","email":"johnsz9999@gmail.com"},"dist":{"shasum":"457e5337280eae85a40bc79034371aa43fd8bb19","tarball":"https://registry.npmjs.org/feathers-hooks-common/-/feathers-hooks-common-2.0.2.tgz"},"maintainers":[{"name":"daffl","email":"daff@neyeon.de"},{"name":"eddystop","email":"johnsz9999@gmail.com"},{"name":"ekryski","email":"e.kryski@gmail.com"}],"_npmOperationalInternal":{"host":"packages-12-west.internal.npmjs.com","tmp":"tmp/feathers-hooks-common-2.0.2.tgz_1480353257801_0.12768016918562353"}},"2.0.3":{"name":"feathers-hooks-common","version":"2.0.3","description":"Useful hooks for use with Feathersjs services.","main":"lib/","directories":{"lib":"lib"},"scripts":{"prepublish":"npm run compile","publish":"git push origin --tags && npm run changelog && git push origin","release:prerelease":"npm version prerelease && npm publish","release:patch":"npm version patch && npm publish","release:minor":"npm version minor && npm publish","release:major":"npm version major && npm publish","changelog":"github_changelog_generator && git add CHANGELOG.md && git commit -am \"Updating changelog\"","compile":"rimraf lib/ && babel -d lib/ src/","watch":"babel --watch -d lib/ src/","lint":"eslint-if-supported semistandard --fix","mocha":"mocha --opts mocha.opts","coverage":"istanbul cover node_modules/mocha/bin/_mocha -- --opts mocha.opts","test":"npm run compile && npm run lint && npm run coverage"},"semistandard":{"env":["mocha"],"ignore":["/lib"]},"repository":{"type":"git","url":"git+https://github.com/feathersjs/feathers-hooks-common.git"},"keywords":["feathers","feathersjs","hook","hooks"],"author":{"name":"John Szwaronek","email":"johnsz9999@gmail.com"},"license":"MIT","bugs":{"url":"https://github.com/feathersjs/feathers-hooks-common/issues"},"homepage":"https://github.com/feathers/feathers-hooks-common#readme","dependencies":{"debug":"^2.2.0","feathers-errors":"^2.4.0","traverse":"0.6.6"},"devDependencies":{"babel-cli":"^6.16.0","babel-core":"^6.17.0","babel-plugin-add-module-exports":"^0.2.1","babel-polyfill":"6.16.0","babel-preset-es2015":"^6.16.0","chai":"^3.5.0","coveralls":"^2.11.14","eslint-if-supported":"^1.0.1","feathers":"2.0.2","feathers-hooks":"1.7.0","feathers-memory":"1.0.1","feathers-tests-fake-app-users":"^1.0.0","istanbul":"^1.1.0-alpha.1","mocha":"^3.1.2","rimraf":"^2.5.4","semistandard":"^9.1.0"},"engines":{"node":">= 4.6.1"},"gitHead":"4cb67e9064ebd06fa3fa82b7351c00b45a510f46","_id":"feathers-hooks-common@2.0.3","_shasum":"e9f12abebdbc163f28d4cb4c85094e29aa24635d","_from":".","_npmVersion":"3.10.8","_nodeVersion":"7.0.0","_npmUser":{"name":"daffl","email":"daff@neyeon.de"},"dist":{"shasum":"e9f12abebdbc163f28d4cb4c85094e29aa24635d","tarball":"https://registry.npmjs.org/feathers-hooks-common/-/feathers-hooks-common-2.0.3.tgz"},"maintainers":[{"name":"daffl","email":"daff@neyeon.de"},{"name":"eddystop","email":"johnsz9999@gmail.com"},{"name":"ekryski","email":"e.kryski@gmail.com"}],"_npmOperationalInternal":{"host":"packages-12-west.internal.npmjs.com","tmp":"tmp/feathers-hooks-common-2.0.3.tgz_1481863984739_0.565717720426619"}}},"readme":"## feathers-hooks-common\n\n[![Build Status](https://travis-ci.org/feathersjs/feathers-hooks-common.svg?branch=master)](https://travis-ci.org/eddyystop/feathers-hooks-common)\n[![Code Climate](https://codeclimate.com/github/feathersjs/feathers.png)](https://codeclimate.com/github/feathersjs/feathers-hooks-common)\n[![Coverage Status](https://coveralls.io/repos/github/feathersjs/feathers-hooks-common/badge.svg?branch=master)](https://coveralls.io/github/feathersjs/feathers-hooks-common?branch=master)\n[![Dependency Status](https://img.shields.io/david/feathersjs/feathers.svg?style=flat-square)](https://david-dm.org/feathersjs/feathers-hooks-common)\n[![Download Status](https://img.shields.io/npm/dm/feathers.svg?style=flat-square)](https://www.npmjs.com/package/feathers-hooks-common)\n[![Slack Status](http://slack.feathersjs.com/badge.svg)](http://slack.feathersjs.com)\n\n> Useful hooks for use with Feathers services.\n\n## Documentation\n\nRefer to [Feathersjs documentation](https://docs.feathersjs.com)\nfor the coming [Auk](https://docs.feathersjs.com/v/auk/hooks/common.html) (preferable)\nor the [current](https://docs.feathersjs.com/hooks/common.html) releases. \n\n## Installation\n\nRun `npm install feathers-hooks-common --save` in your project folder.\n\n## Tests\n\n`npm test` to run tests.\n\n## License\n\nMIT. See LICENSE.\n","maintainers":[{"name":"daffl","email":"daff@neyeon.de"},{"name":"eddystop","email":"johnsz9999@gmail.com"},{"name":"ekryski","email":"e.kryski@gmail.com"}],"time":{"modified":"2016-12-16T04:53:04.969Z","created":"2016-07-13T17:54:20.511Z","0.0.1":"2016-07-13T17:54:20.511Z","0.1.0":"2016-07-14T18:25:18.719Z","0.1.1":"2016-07-15T01:30:22.090Z","0.1.2":"2016-07-15T01:32:25.300Z","0.1.3":"2016-07-15T12:30:52.402Z","0.2.0":"2016-07-15T12:46:50.534Z","1.0.0":"2016-07-25T14:48:53.205Z","1.0.1":"2016-07-25T15:35:02.627Z","1.1.0":"2016-08-17T19:45:05.050Z","1.1.1":"2016-08-17T19:55:11.213Z","1.2.0":"2016-08-18T15:24:52.616Z","1.2.1":"2016-08-18T16:18:24.416Z","1.2.2":"2016-08-18T16:32:46.767Z","1.3.0":"2016-08-18T19:08:41.205Z","1.3.1":"2016-08-18T19:24:36.816Z","1.4.0":"2016-08-19T20:03:16.428Z","1.4.1":"2016-08-19T20:09:27.174Z","1.5.0":"2016-08-20T18:08:03.063Z","1.5.1":"2016-08-20T18:13:49.304Z","1.5.2":"2016-09-08T13:28:59.775Z","1.5.3":"2016-09-11T22:50:47.511Z","1.5.4":"2016-09-12T16:18:50.717Z","1.5.5":"2016-09-12T16:25:46.490Z","1.5.6":"2016-09-12T16:58:40.573Z","1.5.7":"2016-09-13T15:33:36.628Z","1.5.8":"2016-09-14T14:11:49.541Z","1.6.0":"2016-10-02T19:20:45.628Z","1.6.1":"2016-10-02T19:33:16.593Z","1.6.2":"2016-10-03T00:36:57.505Z","1.7.0":"2016-10-04T13:26:24.533Z","1.7.1":"2016-10-06T14:45:08.432Z","1.7.2":"2016-10-07T14:21:04.980Z","2.0.0":"2016-10-29T19:10:52.681Z","2.0.1":"2016-11-04T21:47:11.199Z","2.0.2":"2016-11-28T17:14:20.077Z","2.0.3":"2016-12-16T04:53:04.969Z"},"homepage":"https://github.com/feathers/feathers-hooks-common#readme","keywords":["feathers","feathersjs","hook","hooks"],"repository":{"type":"git","url":"git+https://github.com/feathersjs/feathers-hooks-common.git"},"author":{"name":"John Szwaronek","email":"johnsz9999@gmail.com"},"bugs":{"url":"https://github.com/feathersjs/feathers-hooks-common/issues"},"license":"MIT","readmeFilename":"README.md","_attachments":{},"_etag":"W/\"58537330-18481\"","_lastModified":"Fri, 16 Dec 2016 04:53:04 GMT"}